{"keys": ["65639", "", "65695", "65749", "65803", "65855", "65909", "65910", "65750", "65804", "65856", "65640", "65696", "65805", "65857", "65911", "65697", "65751", "65641", "65912", "65752", "65806", "65858", "65642", "65698", "65807", "65859", "65913", "65643", "65699", "65753", "65860", "65914", "65700", "65754", "65808", "65644", "65809", "65861", "65915", "65645", "65701", "65755", "65810", "65862", "65916", "65646", "65702", "65756", "65811", "65863", "65917", "65647", "65703", "65757", "65864", "65918", "65758", "65812", "65648", "65704", "65813", "65865", "65919", "65649", "65705", "65759", "65867", "65920", "65706", "65760", "65814", "65650", "65815", "65868", "65921", "65651", "65707", "65761", "65869", "65922", "65708", "65762", "65816", "65652", "65817", "65870", "65923", "65653", "65709", "65763", "65871", "65924", "65710", "65764", "65818", "65654", "65819", "65872", "65925", "65655", "65711", "65765"], "data": {"65710": {"propaddres": 20170, "proaddress": "20170 MONTE VISTA", "parcelnumb": "16044823.", "fid": 65710, "ownername1": "REVELS, TERESA P"}, "65711": {"propaddres": 20162, "proaddress": "20162 MONTE VISTA", "parcelnumb": "16044822.", "fid": 65711, "ownername1": "HALL, STEVIE"}, "65911": {"propaddres": 20420, "proaddress": "20420 MENDOTA", "parcelnumb": "16043152.", "fid": 65911, "ownername1": "DOOLEY, TRACEY"}, "65909": {"propaddres": 20436, "proaddress": "20436 MENDOTA", "parcelnumb": "16043154.", "fid": 65909, "ownername1": "THOMAS, BOBBY"}, "65803": {"propaddres": 20436, "proaddress": "20436 PINEHURST", "parcelnumb": "16044046.", "fid": 65803, "ownername1": "CARR, VERNON E"}, "65804": {"propaddres": 20428, "proaddress": "20428 PINEHURST", "parcelnumb": "16044045.", "fid": 65804, "ownername1": "THOMAS, HAZEL"}, "65805": {"propaddres": 20420, "proaddress": "20420 PINEHURST", "parcelnumb": "16044044.", "fid": 65805, "ownername1": "THOMAS, RICARDO"}, "65806": {"propaddres": 20412, "proaddress": "20412 PINEHURST", "parcelnumb": "16044043.", "fid": 65806, "ownername1": "ABRAHMS GROUP LLC"}, "65807": {"propaddres": 20402, "proaddress": "20402 PINEHURST", "parcelnumb": "16044042.", "fid": 65807, "ownername1": "STAPLETON, MARY"}, "65808": {"propaddres": 20252, "proaddress": "20252 PINEHURST", "parcelnumb": "16044041.", "fid": 65808, "ownername1": "ROSS, ROSALIND E & HENRY O"}, "65809": {"propaddres": 20244, "proaddress": "20244 PINEHURST", "parcelnumb": "16044040.", "fid": 65809, "ownername1": "LITTLETON, TWILA"}, "65640": {"propaddres": 20429, "proaddress": "20429 MONTE VISTA", "parcelnumb": "16044862.", "fid": 65640, "ownername1": "GLENN, TIFFANY"}, "65641": {"propaddres": 20421, "proaddress": "20421 MONTE VISTA", "parcelnumb": "16044863.", "fid": 65641, "ownername1": "YOUNG, ROBELIA"}, "65862": {"propaddres": 20235, "proaddress": "20235 MENDOTA", "parcelnumb": "16043184.", "fid": 65862, "ownername1": "MUSE, PORTER JAMES"}, "65647": {"propaddres": 20227, "proaddress": "20227 MONTE VISTA", "parcelnumb": "16044869.", "fid": 65647, "ownername1": "SEAY, MILDRED"}, "65860": {"propaddres": 20255, "proaddress": "20255 MENDOTA", "parcelnumb": "16043182.", "fid": 65860, "ownername1": "POWELL, BARBARA J"}, "65861": {"propaddres": 20245, "proaddress": "20245 MENDOTA", "parcelnumb": "16043183.", "fid": 65861, "ownername1": "ABBY, AUDREY"}, "65765": {"propaddres": 20165, "proaddress": "20165 PINEHURST", "parcelnumb": "16044085.", "fid": 65765, "ownername1": "BAKIN, HENRY & CLEO"}, "65764": {"propaddres": 20171, "proaddress": "20171 PINEHURST", "parcelnumb": "16044084.", "fid": 65764, "ownername1": "MOORE, OTIS"}, "65761": {"propaddres": 20195, "proaddress": "20195 PINEHURST", "parcelnumb": "16044081.", "fid": 65761, "ownername1": "JONES, CHARLIE M"}, "65760": {"propaddres": 20203, "proaddress": "20203 PINEHURST", "parcelnumb": "16044080.", "fid": 65760, "ownername1": "RANSOM DETROIT LLC"}, "65763": {"propaddres": 20179, "proaddress": "20179 PINEHURST", "parcelnumb": "16044083.", "fid": 65763, "ownername1": "DANIELS, L V"}, "65762": {"propaddres": 20187, "proaddress": "20187 PINEHURST", "parcelnumb": "16044082.", "fid": 65762, "ownername1": "BURTON, CAROLYN"}, "65651": {"propaddres": 20195, "proaddress": "20195 MONTE VISTA", "parcelnumb": "16044873.", "fid": 65651, "ownername1": "FLETCHER, BAHATI & DUKES BAHITA"}, "65650": {"propaddres": 20203, "proaddress": "20203 MONTE VISTA", "parcelnumb": "16044872.", "fid": 65650, "ownername1": "SMITH, WILLIAM"}, "65653": {"propaddres": 20179, "proaddress": "20179 MONTE VISTA", "parcelnumb": "16044875.", "fid": 65653, "ownername1": "PEGUES, ANDREW JR"}, "65652": {"propaddres": 20187, "proaddress": "20187 MONTE VISTA", "parcelnumb": "16044874.", "fid": 65652, "ownername1": "COTTON, MATTHEW"}, "65871": {"propaddres": 20171, "proaddress": "20171 MENDOTA", "parcelnumb": "16043192.", "fid": 65871, "ownername1": "ARNSWALD, TIMOTHY J"}, "65870": {"propaddres": 20179, "proaddress": "20179 MENDOTA", "parcelnumb": "16043191.", "fid": 65870, "ownername1": "DAVIS, CORA A"}, "65872": {"propaddres": 20163, "proaddress": "20163 MENDOTA", "parcelnumb": "16043193.", "fid": 65872, "ownername1": "FLARICEE, MARTHA"}, "65869": {"propaddres": 20187, "proaddress": "20187 MENDOTA", "parcelnumb": "16043190.", "fid": 65869, "ownername1": "HARBOUR PORTFOLIO VII, LP"}, "65750": {"propaddres": 20429, "proaddress": "20429 PINEHURST", "parcelnumb": "16044070.", "fid": 65750, "ownername1": "MACKALL, MARIAN J"}, "65751": {"propaddres": 20421, "proaddress": "20421 PINEHURST", "parcelnumb": "16044071.", "fid": 65751, "ownername1": "BERNARD, SALONJE"}, "65642": {"propaddres": 20413, "proaddress": "20413 MONTE VISTA", "parcelnumb": "16044864.", "fid": 65642, "ownername1": "SWAIN, ALICIA"}, "65643": {"propaddres": 20403, "proaddress": "20403 MONTE VISTA", "parcelnumb": "16044865.", "fid": 65643, "ownername1": "JOHNSON, BEVERLY"}, "65864": {"propaddres": 20219, "proaddress": "20219 MENDOTA", "parcelnumb": "16043186.", "fid": 65864, "ownername1": "HOME SWEET HOMES REO INC"}, "65865": {"propaddres": 20211, "proaddress": "20211 MENDOTA", "parcelnumb": "16043187.", "fid": 65865, "ownername1": "HILL, HELEN"}, "65646": {"propaddres": 20235, "proaddress": "20235 MONTE VISTA", "parcelnumb": "16044868.", "fid": 65646, "ownername1": "WARD, ROSE AND AUSTIN, RICHARD E"}, "65863": {"propaddres": 20227, "proaddress": "20227 MENDOTA", "parcelnumb": "16043185.", "fid": 65863, "ownername1": "STREETER, CHARLES J JR"}, "65644": {"propaddres": 20253, "proaddress": "20253 MONTE VISTA", "parcelnumb": "16044866.", "fid": 65644, "ownername1": "BRINKLEY, EVA P"}, "65645": {"propaddres": 20245, "proaddress": "20245 MONTE VISTA", "parcelnumb": "16044867.", "fid": 65645, "ownername1": "LEONARD, OLYMPHIA"}, "65655": {"propaddres": 20163, "proaddress": "20163 MONTE VISTA", "parcelnumb": "16044877.", "fid": 65655, "ownername1": "BANKERS TRUST CO"}, "65648": {"propaddres": 20219, "proaddress": "20219 MONTE VISTA", "parcelnumb": "16044870.", "fid": 65648, "ownername1": "TAXPAYER"}, "65649": {"propaddres": 20213, "proaddress": "20213 MONTE VISTA", "parcelnumb": "16044871.", "fid": 65649, "ownername1": "HENDRIX, RUDOLF"}, "65868": {"propaddres": 20195, "proaddress": "20195 MENDOTA", "parcelnumb": "16043189.", "fid": 65868, "ownername1": "CITY OF DETROIT"}, "65654": {"propaddres": 20171, "proaddress": "20171 MONTE VISTA", "parcelnumb": "16044876.", "fid": 65654, "ownername1": "BLUE, MARIE"}, "65749": {"propaddres": 20437, "proaddress": "20437 PINEHURST", "parcelnumb": "16044069.", "fid": 65749, "ownername1": "BRADFORD, CLAUDIA A"}, "65918": {"propaddres": 20220, "proaddress": "20220 MENDOTA", "parcelnumb": "16043145.", "fid": 65918, "ownername1": "BIBBS, MARCELLA & FREEMAN, KIMBERLY"}, "65919": {"propaddres": 20210, "proaddress": "20210 MENDOTA", "parcelnumb": "16043144.", "fid": 65919, "ownername1": "HAMILTON MULDROW, CANDACE"}, "65857": {"propaddres": 20421, "proaddress": "20421 MENDOTA", "parcelnumb": "16043179.", "fid": 65857, "ownername1": "GREEN, ROBERT"}, "65856": {"propaddres": 20427, "proaddress": "20427 MENDOTA", "parcelnumb": "16043178.", "fid": 65856, "ownername1": "GREGORY, M & B"}, "65855": {"propaddres": 20435, "proaddress": "20435 MENDOTA", "parcelnumb": "16043177.", "fid": 65855, "ownername1": "LLOYD, BETTIE JEAN"}, "65912": {"propaddres": 20410, "proaddress": "20410 MENDOTA", "parcelnumb": "16043151.", "fid": 65912, "ownername1": "HUDGINS, BILLIE S"}, "65913": {"propaddres": 20400, "proaddress": "20400 MENDOTA", "parcelnumb": "16043150.", "fid": 65913, "ownername1": "HUDGINS, BILLIE S"}, "65859": {"propaddres": 20403, "proaddress": "20403 MENDOTA", "parcelnumb": "16043181.", "fid": 65859, "ownername1": "GOFF, SYLVESTER"}, "65858": {"propaddres": 20411, "proaddress": "20411 MENDOTA", "parcelnumb": "16043180.", "fid": 65858, "ownername1": "WARE, JAMES"}, "65916": {"propaddres": 20236, "proaddress": "20236 MENDOTA", "parcelnumb": "16043147.", "fid": 65916, "ownername1": "JONES ESTATE MANAGEMENT INC"}, "65917": {"propaddres": 20226, "proaddress": "20226 MENDOTA", "parcelnumb": "16043146.", "fid": 65917, "ownername1": "WARE, BERTIE"}, "65914": {"propaddres": 20250, "proaddress": "20250 MENDOTA", "parcelnumb": "16043149.", "fid": 65914, "ownername1": "MURPHY, VALERIE V"}, "65915": {"propaddres": 20244, "proaddress": "20244 MENDOTA", "parcelnumb": "16043148.", "fid": 65915, "ownername1": "LAMB, ERIN"}, "65695": {"propaddres": 20436, "proaddress": "20436 MONTE VISTA", "parcelnumb": "16044838.", "fid": 65695, "ownername1": "HUD"}, "65697": {"propaddres": 20420, "proaddress": "20420 MONTE VISTA", "parcelnumb": "16044836.", "fid": 65697, "ownername1": "DAVIS, THOMAS E & MINNIE K"}, "65696": {"propaddres": 20428, "proaddress": "20428 MONTE VISTA", "parcelnumb": "16044837.", "fid": 65696, "ownername1": "DAVIS, JARED J"}, "65758": {"propaddres": 20219, "proaddress": "20219 PINEHURST", "parcelnumb": "16044078.", "fid": 65758, "ownername1": "FREEMAN, SARAH L"}, "65759": {"propaddres": 20211, "proaddress": "20211 PINEHURST", "parcelnumb": "16044079.", "fid": 65759, "ownername1": "MICKIE, GERALDINE"}, "65754": {"propaddres": 20253, "proaddress": "20253 PINEHURST", "parcelnumb": "16044074.", "fid": 65754, "ownername1": "WHITE, LULA MAE"}, "65755": {"propaddres": 20245, "proaddress": "20245 PINEHURST", "parcelnumb": "16044075.", "fid": 65755, "ownername1": "LEVESTON, GARFIELD & HELEN"}, "65756": {"propaddres": 20235, "proaddress": "20235 PINEHURST", "parcelnumb": "16044076.", "fid": 65756, "ownername1": "CAREY, MICHAEL"}, "65757": {"propaddres": 20227, "proaddress": "20227 PINEHURST", "parcelnumb": "16044077.", "fid": 65757, "ownername1": "DOCKERY, ALMIRA M"}, "65699": {"propaddres": 20400, "proaddress": "20400 MONTE VISTA", "parcelnumb": "16044834.", "fid": 65699, "ownername1": "PEARSON, WILLIAM"}, "65698": {"propaddres": 20410, "proaddress": "20410 MONTE VISTA", "parcelnumb": "16044835.", "fid": 65698, "ownername1": "MATTHEWS, ANN M"}, "65752": {"propaddres": 20413, "proaddress": "20413 PINEHURST", "parcelnumb": "16044072.", "fid": 65752, "ownername1": "BOYD, WILLIAM A & SMITH, ANDREA"}, "65753": {"propaddres": 20401, "proaddress": "20401 PINEHURST", "parcelnumb": "16044073.", "fid": 65753, "ownername1": "HILSON, ASENATH M"}, "65925": {"propaddres": 20164, "proaddress": "20164 MENDOTA", "parcelnumb": "16043138.", "fid": 65925, "ownername1": "MOSLEY, RICHARD B"}, "65924": {"propaddres": 20170, "proaddress": "20170 MENDOTA", "parcelnumb": "16043139.", "fid": 65924, "ownername1": "GORDON, LUCILLE"}, "65923": {"propaddres": 20180, "proaddress": "20180 MENDOTA", "parcelnumb": "16043140.", "fid": 65923, "ownername1": "FOREMAN, CHARLOTTE"}, "65922": {"propaddres": 20186, "proaddress": "20186 MENDOTA", "parcelnumb": "16043141.", "fid": 65922, "ownername1": "SPANN, TOBY A"}, "65921": {"propaddres": 20194, "proaddress": "20194 MENDOTA", "parcelnumb": "16043142.", "fid": 65921, "ownername1": "HOWARD, CHARLES DEXTER &WENDY MARIE"}, "65920": {"propaddres": 20200, "proaddress": "20200 MENDOTA", "parcelnumb": "16043143.", "fid": 65920, "ownername1": "FANNIE MAE"}, "65639": {"propaddres": 20437, "proaddress": "20437 MONTE VISTA", "parcelnumb": "16044861.", "fid": 65639, "ownername1": "JONES, MARK"}, "65707": {"propaddres": 20194, "proaddress": "20194 MONTE VISTA", "parcelnumb": "16044826.", "fid": 65707, "ownername1": "LEAVELL, SYLVIA G"}, "65706": {"propaddres": 20200, "proaddress": "20200 MONTE VISTA", "parcelnumb": "16044827.", "fid": 65706, "ownername1": "HAYES-HOLLINS, JEANNETTE"}, "65705": {"propaddres": 20210, "proaddress": "20210 MONTE VISTA", "parcelnumb": "16044828.", "fid": 65705, "ownername1": "LASALLE BANK NATIONAL ASSOCIATION"}, "65704": {"propaddres": 20218, "proaddress": "20218 MONTE VISTA", "parcelnumb": "16044829.", "fid": 65704, "ownername1": "BURNLEY, M AND LEARY-BURNLEY, R"}, "65703": {"propaddres": 20226, "proaddress": "20226 MONTE VISTA", "parcelnumb": "16044830.", "fid": 65703, "ownername1": "YSLAVA, F DANIEL"}, "65702": {"propaddres": 20236, "proaddress": "20236 MONTE VISTA", "parcelnumb": "16044831.", "fid": 65702, "ownername1": "JOHNSON, HENRY"}, "65701": {"propaddres": 20244, "proaddress": "20244 MONTE VISTA", "parcelnumb": "16044832.", "fid": 65701, "ownername1": "THOMPSON, BETTY J"}, "65700": {"propaddres": 20254, "proaddress": "20254 MONTE VISTA", "parcelnumb": "16044833.", "fid": 65700, "ownername1": "KING, ELIZABETH J"}, "65709": {"propaddres": 20178, "proaddress": "20178 MONTE VISTA", "parcelnumb": "16044824.", "fid": 65709, "ownername1": "BLUE, MARIE"}, "65708": {"propaddres": 20186, "proaddress": "20186 MONTE VISTA", "parcelnumb": "16044825.", "fid": 65708, "ownername1": "LEAVELL, SYLVIA"}, "65867": {"propaddres": 20201, "proaddress": "20201 MENDOTA", "parcelnumb": "16043188.", "fid": 65867, "ownername1": "MEADOWS, YVETTE P"}, "65910": {"propaddres": 20426, "proaddress": "20426 MENDOTA", "parcelnumb": "16043153.", "fid": 65910, "ownername1": "COOK, ALFRED"}, "65817": {"propaddres": 20178, "proaddress": "20178 PINEHURST", "parcelnumb": "16044032.", "fid": 65817, "ownername1": "POLLARD, HAROLD"}, "65816": {"propaddres": 20186, "proaddress": "20186 PINEHURST", "parcelnumb": "16044033.", "fid": 65816, "ownername1": "HARBOUR PORTFOLIO VII, LP"}, "65815": {"propaddres": 20194, "proaddress": "20194 PINEHURST", "parcelnumb": "16044034.", "fid": 65815, "ownername1": "MIAH, MALIK"}, "65814": {"propaddres": 20204, "proaddress": "20204 PINEHURST", "parcelnumb": "16044035.", "fid": 65814, "ownername1": "BAKER, KEN"}, "65813": {"propaddres": 20210, "proaddress": "20210 PINEHURST", "parcelnumb": "16044036.", "fid": 65813, "ownername1": "STONE CREST INCOME & OPPORTUNITY"}, "65812": {"propaddres": 20218, "proaddress": "20218 PINEHURST", "parcelnumb": "16044037.", "fid": 65812, "ownername1": "BIVINS, ANNIE & ROCHELLE CO TRUSTEE"}, "65811": {"propaddres": 20226, "proaddress": "20226 PINEHURST", "parcelnumb": "16044038.", "fid": 65811, "ownername1": "ACORN INVESTMENT COMPANY"}, "65810": {"propaddres": 20234, "proaddress": "20234 PINEHURST", "parcelnumb": "16044039.", "fid": 65810, "ownername1": "CHARLES, NARVETTA TAJUAN"}, "65819": {"propaddres": 20162, "proaddress": "20162 PINEHURST", "parcelnumb": "16044030.", "fid": 65819, "ownername1": "BOYKIN, A"}, "65818": {"propaddres": 20170, "proaddress": "20170 PINEHURST", "parcelnumb": "16044031.", "fid": 65818, "ownername1": "DORSEY, ALMA B"}}, "grid": ["    !!!!!##########$$$$$$$$$$!!!!!%%%%%%%%%%&&&&&&&&&&!!!!!'''''", "    !!!!!##########$$$$$$$$$$!!!!!%%%%%%%%%%&&&&&&&&&&!!!!!'''((", "    !!!!!##########$$$)))))))!!!!!**********++++++++++!!!!!(((((", ",,,,!!!!!----------))))))))))!!!!!**********++++++++++!!!!!(((((", ",,,,!!!!!----------))))))))))!!!!!**********++++++++++!!!!!(((((", ",,,,!!!!!----------))))))))))!!!!!*******...//////////!!!!!00000", ",,,,!!!!!11111111112222222222!!!!!..........//////////!!!!!00000", "3333!!!!!11111111112222222222!!!!!..........//////////!!!!!00000", "3333!!!!!11111111112222222222!!!!!..........//////////!!!!!44444", "3333!!!!!111111111155555555555!!!!66666666667777777777!!!!!44444", "8888!!!!!999999999955555555555!!!!66666666667777777777!!!!!44444", "8888!!!!!999999999955555555555!!!!666666666677777777777!!!!44444", "88888!!!!999999999955555555555!!!!6666::::::;;;;;;;;;;;!!!!<<<<<", "8888=!!!!>>>>>>>>>>???????????!!!!::::::::::;;;;;;;;;;;!!!!<<<<<", "=====!!!!>>>>>>>>>>???????????!!!!::::::::::;;;;;;;;;;;!!!!<<<<<", "=====!!!!>>>>>>>>>>???????????!!!!::::::::::;;;;;;;;;;;!!!!<<<<<", "=====!!!!>>>>>>>>>>???????????!!!!::::::::::;;;;;;;;;;;!!!!<<<!!", "=====!!!!>>>>>>>>>>?????!!!!!!!!!!!!!!!!!!!!!!!!!!!!!!!!!!!!!!!!", "!!!!!!!!!!!!!!!!!!!!!!!!!!!!!!!!!!!!!!!!!!!!!!!!!!!!!!!!!!!!!!!!", "!!!!!!!!!!!!!!!!!!!!!!!!!!!!!!!!!!!!!!!!!!!!!!!!!!!!!!!!!!!!!!!!", "!!!!!!!!!!!!!!!!!!!!!!!!!!!!!!!!!!!!!!!!!!!!!!!!!!!!!!!!!!!!!!!!", "!!!!!!!!!!!!!!!!!!!!!!!!!!!!!!!!!!!!!!!!!!!!!!@@@@@@@@@!!!!AAAAA", "!!!!!!!!!!!!!BBBBBBBCCCCCCCCCC!!!!!DDDDDDDDDD@@@@@@@@@@!!!!AAAAA", "EEEEE!!!!!BBBBBBBBBBCCCCCCCCCC!!!!!DDDDDDDDDD@@@@@@@@@@!!!!AAAAA", "EEEEE!!!!!BBBBBBBBBBCCCCCCCCCC!!!!!DDDDDDDDDD@@@@@@@@@@!!!!!AAAA", "EEEEE!!!!!BBBBBBBBBBCCCCCCCCCC!!!!!DDDDDDDDFFGGGGGGGGGG!!!!!HHHH", "EEEEI!!!!!JJJJJJJJJJKKKKKKKKKK!!!!!FFFFFFFFFFGGGGGGGGGG!!!!!HHHH", "IIIII!!!!!JJJJJJJJJJKKKKKKKKKK!!!!!FFFFFFFFFFGGGGGGGGGG!!!!!HHHH", "IIIII!!!!!JJJJJJJJJJKKKKKKKKKK!!!!!FFFFFFFFFFGGGGGGGGGG!!!!!HHHH", "IIIII!!!!!JJJJJJJJJJKKKKKKKKKK!!!!!FFFFLLLLLLMMMMMMMMMM!!!!!NNNN", "OOOOO!!!!!PPPPPPPPPPQQQQQQQQQQ!!!!!LLLLLLLLLLMMMMMMMMMM!!!!!NNNN", "OOOOO!!!!!PPPPPPPPPPQQQQQQQQQQ!!!!!LLLLLLLLLLMMMMMMMMMM!!!!!NNNN", "OOOOO!!!!!PPPPPPPPPPQQQQQQQQQQ!!!!!LLLLLLLLLLMMMMMMMMMM!!!!!NNNN", "OOOOO!!!!!PPPPPPPPPPQQQQQQQQQQ!!!!!RRRRRRRRRRSSSSSSSSSS!!!!!TTTT", "UUUUU!!!!!VVVVVVVVVVWWWWWWWWWW!!!!!RRRRRRRRRRSSSSSSSSSS!!!!!TTTT", "UUUUU!!!!!VVVVVVVVVVWWWWWWWWWW!!!!!RRRRRRRRRRSSSSSSSSSS!!!!!TTTT", "UUUUU!!!!!VVVVVVVVVVWWWWWWWWWW!!!!!RRRRRRRRRRSSSSSSSSSX!!!!!YYYY", "UUUUU!!!!!VVVVVVVVVVZZZZZZZZZZ!!!!![[[[[[[[[[XXXXXXXXXX!!!!!YYYY", "]]]]]!!!!!^^^^^^^^^^ZZZZZZZZZZ!!!!![[[[[[[[[[XXXXXXXXXX!!!!!YYYY", "]]]]]!!!!!^^^^^^^^^^ZZZZZZZZZZ!!!!![[[[[[[[[[XXXXXXXXXX!!!!!YYYY", "]]]]]!!!!!^^^^^^^^^^ZZZZZZZZZZ!!!!!__________``````````!!!!!aaaa", "bbbbb!!!!!ccccccccccdddddddddd!!!!!__________```````````!!!!aaaa", "bbbbb!!!!!ccccccccccdddddddddd!!!!!__________```````````!!!!aaaa", "bbbbb!!!!!ccccccccccddddddddddd!!!!__________``````eeeee!!!!ffff", "bbbbb!!!!!cccccccggghhhhhhhhhhh!!!!iiiiiiiiiieeeeeeeeeee!!!!ffff", "jjjjj!!!!!gggggggggghhhhhhhhhhh!!!!iiiiiiiiiieeeeeeeeeee!!!!ffff", "jjjjj!!!!!gggggggggghhhhhhhhhhh!!!!iiiiiiiiiieeeeeeeeeee!!!!ffff", "jjjjj!!!!!gggggggggghhhhhhhhhhh!!!!kkkkkkkkkklllllllllll!!!!mmmm", "nnnnn!!!!!ooooooooooppppppppppp!!!!kkkkkkkkkklllllllllll!!!!mmmm", "nnnnnn!!!!ooooooooooppppppppppp!!!!kkkkkkkkkklllllllllll!!!!mmmm", "nnnnnn!!!!ooooooooooppppppppppp!!!!kkkkkkkkkklllqqqqqqqq!!!!rrrr", "nnnnnn!!!!ooosssssssttttttttttt!!!!uuuuuuuuuuqqqqqqqqqqq!!!!rrrr", "vvvvvv!!!!ssssssssssttttttttttt!!!!uuuuuuuuuuqqqqqqqqqqq!!!!rrrr", "vvvvvv!!!!ssssssssssttttttttttt!!!!uuuuuuuuuuqqqqqqqqqqq!!!!rrrr", "vvvvvv!!!!ssssssssssttttttttttt!!!!wwwwwwwwwwxxxxxxxxxxx!!!!yyyy", "zzzzzz!!!!{{{{{{{{{{|||||||||||!!!!wwwwwwwwwwxxxxxxxxxxx!!!!yyyy", "zzzzzz!!!!{{{{{{{{{{|||||||||||!!!!wwwwwwwwwwxxxxxxxxxxx!!!!!yyy", "zzzzzz!!!!{{{{{{{{{{|||||||||||!!!!wwwwwwwwwwx}}}}}}}}}}!!!!!~~~", "zzzzzz!!!!{\u007f\u007f\u007f\u007f\u007f\u007f\u007f\u007f\u007f\u0080\u0080\u0080\u0080\u0080\u0080\u0080\u0080\u0080\u0080\u0080!!!!\u0081\u0081\u0081\u0081\u0081\u0081\u0081\u0081\u0081\u0081}}}}}}}}}}}!!!!!~~~", "\u0082\u0082\u0082\u0082\u0082\u0082!!!!\u007f\u007f\u007f\u007f\u007f\u007f\u007f\u007f\u007f\u007f\u0080\u0080\u0080\u0080\u0080\u0080\u0080\u0080\u0080\u0080\u0080!!!!!\u0081\u0081\u0081\u0081\u0081\u0081\u0081\u0081\u0081}}}}}}}}}}}!!!!!~~~", "\u0082\u0082\u0082\u0082\u0082\u0082!!!!\u007f\u007f\u007f\u007f\u007f\u007f\u007f\u007f\u007f\u007f\u0080\u0080\u0080\u0080\u0080\u0080\u0080\u0080\u0080\u0080\u0080!!!!!\u0081\u0081\u0081\u0081\u0081\u0081\u0081\u0081\u0081\u0081}}}}}}}}}}!!!!!~~~", "\u0082\u0082\u0082\u0082\u0082\u0082!!!!!\u007f\u007f\u007f\u007f\u007f\u007f\u007f\u007f\u007f\u0080\u0080\u0080\u0080\u0080\u0080\u0080\u0080\u0080\u0080\u0080!!!!!\u0083\u0083\u0083\u0083\u0083\u0083\u0083\u0083\u0083\u0083\u0084\u0084\u0084\u0084\u0084\u0084\u0084\u0084\u0084\u0084!!!!!\u0085\u0085\u0085", "\u0086\u0086\u0086\u0086\u0086\u0086!!!!!\u0087\u0087\u0087\u0087\u0087\u0087\u0087\u0087\u0087\u0087\u0088\u0088\u0088\u0088\u0088\u0088\u0088\u0088\u0088\u0088!!!!!\u0083\u0083\u0083\u0083\u0083\u0083\u0083\u0083\u0083\u0083\u0084\u0084\u0084\u0084\u0084\u0084\u0084\u0084\u0084\u0084!!!!!\u0085\u0085\u0085", "\u0086\u0086\u0086\u0086\u0086\u0086!!!!!\u0087\u0087\u0087\u0087\u0087\u0087\u0087\u0087\u0087\u0087\u0088\u0088\u0088\u0088\u0088\u0088\u0088\u0088\u0088\u0088!!!!!\u0083\u0083\u0083\u0083\u0083\u0083\u0083\u0083\u0083\u0083\u0084\u0084\u0084\u0084\u0084\u0084\u0084\u0084\u0084\u0084!!!!!\u0085\u0085\u0085"]}