{"keys": ["", "54595", "54660", "54731", "54661", "54596", "54732", "54662", "54597", "54733", "54663", "54598", "54734", "54664", "54599", "54735", "54665", "54600", "54736", "54666", "54601", "54737", "54667", "54602", "54739", "54541", "54668", "54740", "54669", "54603", "54741", "54670", "54604", "54742"], "data": {"54668": {"propaddres": 8055, "proaddress": "8055 NORTHLAWN", "parcelnumb": "18014859.", "fid": 54668, "ownername1": "HAGOOD, MARION W"}, "54669": {"propaddres": 8045, "proaddress": "8045 NORTHLAWN", "parcelnumb": "18014860.", "fid": 54669, "ownername1": "MCCAIN, SHAMIKA"}, "54602": {"propaddres": 8058, "proaddress": "8058 OHIO", "parcelnumb": "18014868-9", "fid": 54602, "ownername1": "JARRETT, LETETIA D"}, "54603": {"propaddres": 8046, "proaddress": "8046 OHIO", "parcelnumb": "18014867.", "fid": 54603, "ownername1": "MCCUIEN, DELAIRE"}, "54666": {"propaddres": 8067, "proaddress": "8067 NORTHLAWN", "parcelnumb": "18014857.", "fid": 54666, "ownername1": "M & W RENTAL INC"}, "54667": {"propaddres": 8061, "proaddress": "8061 NORTHLAWN", "parcelnumb": "18014858.", "fid": 54667, "ownername1": "MARTIN, AMON"}, "54660": {"propaddres": 8111, "proaddress": "8111 NORTHLAWN", "parcelnumb": "18014851.", "fid": 54660, "ownername1": "KNOX, TOMMY"}, "54661": {"propaddres": 8103, "proaddress": "8103 NORTHLAWN", "parcelnumb": "18014852.", "fid": 54661, "ownername1": "JOHNSON, L"}, "54604": {"propaddres": 8040, "proaddress": "8040 OHIO", "parcelnumb": "18014866.", "fid": 54604, "ownername1": "KROUSE,  JACINTA"}, "54663": {"propaddres": 8089, "proaddress": "8089 NORTHLAWN", "parcelnumb": "18014854.", "fid": 54663, "ownername1": "PHILLIPS, LOLITA D"}, "54598": {"propaddres": 8088, "proaddress": "8088 OHIO", "parcelnumb": "18014873.", "fid": 54598, "ownername1": "STEVENSON, RAYMOND"}, "54599": {"propaddres": 8080, "proaddress": "8080 OHIO", "parcelnumb": "18014872.", "fid": 54599, "ownername1": "SINGLETON, HERBERT G"}, "54596": {"propaddres": 8102, "proaddress": "8102 OHIO", "parcelnumb": "18014875.", "fid": 54596, "ownername1": "PENICK, WILMA & ROBERT"}, "54597": {"propaddres": 8094, "proaddress": "8094 OHIO", "parcelnumb": "18014874.", "fid": 54597, "ownername1": "LOCKHART, THEOLA L"}, "54595": {"propaddres": 8110, "proaddress": "8110 OHIO", "parcelnumb": "18014876.", "fid": 54595, "ownername1": "HOLLOWAY, JOYCE"}, "54735": {"propaddres": 8080, "proaddress": "8080 NORTHLAWN", "parcelnumb": "18014568.", "fid": 54735, "ownername1": "CITY OF DETROIT"}, "54664": {"propaddres": 8083, "proaddress": "8083 NORTHLAWN", "parcelnumb": "18014855.", "fid": 54664, "ownername1": "PHILLIPS, LOLITA"}, "54665": {"propaddres": 8075, "proaddress": "8075 NORTHLAWN", "parcelnumb": "18014856.", "fid": 54665, "ownername1": "NEWMAN, KAREN"}, "54600": {"propaddres": 8072, "proaddress": "8072 OHIO", "parcelnumb": "18014871.", "fid": 54600, "ownername1": "CROCKETT, H & C"}, "54736": {"propaddres": 8074, "proaddress": "8074 NORTHLAWN", "parcelnumb": "18014567.", "fid": 54736, "ownername1": "HORTON, AISHA F"}, "54737": {"propaddres": 8066, "proaddress": "8066 NORTHLAWN", "parcelnumb": "18014566.", "fid": 54737, "ownername1": "WITHERSPOON, NELLIE"}, "54734": {"propaddres": 8086, "proaddress": "8086 NORTHLAWN", "parcelnumb": "18014569.", "fid": 54734, "ownername1": "CITY OF DETROIT-P&DD"}, "54601": {"propaddres": 8066, "proaddress": "8066 OHIO", "parcelnumb": "18014870.", "fid": 54601, "ownername1": "CROCKETT, HOMER E"}, "54732": {"propaddres": 8102, "proaddress": "8102 NORTHLAWN", "parcelnumb": "18014571.", "fid": 54732, "ownername1": "HARRIS, LULA BENNETT"}, "54733": {"propaddres": 8096, "proaddress": "8096 NORTHLAWN", "parcelnumb": "18014570.", "fid": 54733, "ownername1": "PHILLIPS, HOWARD"}, "54731": {"propaddres": 8108, "proaddress": "8108 NORTHLAWN", "parcelnumb": "18014572.", "fid": 54731, "ownername1": "FRIDAY, RICHARD A"}, "54541": {"propaddres": 8522, "proaddress": "8522 TIREMAN", "parcelnumb": "18004923.", "fid": 54541, "ownername1": "DET URBAN LUTHERAN SCHOOLS"}, "54739": {"propaddres": 8058, "proaddress": "8058 NORTHLAWN", "parcelnumb": "18014565.", "fid": 54739, "ownername1": "BARKER, KAREN"}, "54662": {"propaddres": 8095, "proaddress": "8095 NORTHLAWN", "parcelnumb": "18014853.", "fid": 54662, "ownername1": "MATHIS, ALFRED W"}, "54670": {"propaddres": 8039, "proaddress": "8039 NORTHLAWN", "parcelnumb": "18014861.", "fid": 54670, "ownername1": "GENSTAR FINANCIAL"}, "54742": {"propaddres": 8038, "proaddress": "8038 NORTHLAWN", "parcelnumb": "18014562.", "fid": 54742, "ownername1": "CROSS, CAREN"}, "54741": {"propaddres": 8044, "proaddress": "8044 NORTHLAWN", "parcelnumb": "18014563.", "fid": 54741, "ownername1": "POSEY, BEOSKER"}, "54740": {"propaddres": 8052, "proaddress": "8052 NORTHLAWN", "parcelnumb": "18014564.", "fid": 54740, "ownername1": "HUNT, GEORGE A"}}, "grid": ["       !!!!!!!!!!!!!!!!!!  ###################        $$$$$$$$$$", "       !!!!!!!!!!!!!!!!!!  ###################        $$$$$$$$$$", "       !!!!!!!!!!!!!!!!!!  ###################        $$$$$$$$$$", "       !!!!!!!!!!!!!!!!!!  ###################        $$$$$$$$$$", "       !!!!!!!!!!!!!!!!!!   %%%%%%%%%%%%%%%%%%        $$$$$$$$$$", "       &&&&&&&&&&&&&&&&&&   %%%%%%%%%%%%%%%%%%        $$$$$$$$$$", "       &&&&&&&&&&&&&&&&&&   %%%%%%%%%%%%%%%%%%        ''''''''''", "       &&&&&&&&&&&&&&&&&&   %%%%%%%%%%%%%%%%%%        ''''''''''", "       &&&&&&&&&&&&&&&&&&   %%%%%%%%%%%%%%%%%%        ''''''''''", "       &&&&&&&&&&&&&&&&&&   %%%%%%%%%%%%%%%%%%        ''''''''''", "        &&&&&&&&&&&&&&&&&   %%%(((((((((((((((        ''''''''''", "        ))))))))))))))))))  ((((((((((((((((((        ''''''''''", "        ))))))))))))))))))  ((((((((((((((((((        **********", "        ))))))))))))))))))  ((((((((((((((((((        **********", "        ))))))))))))))))))  ((((((((((((((((((        **********", "        ))))))))))))))))))  ((((((((((((((((((        **********", "        ))))))))))))))))))  ((((++++++++++++++        **********", "        ,,,,,,,,,,,,,,,,,,  ++++++++++++++++++        **********", "        ,,,,,,,,,,,,,,,,,,  ++++++++++++++++++        ----------", "        ,,,,,,,,,,,,,,,,,,  ++++++++++++++++++        ----------", "        ,,,,,,,,,,,,,,,,,,  +++++++++++++++++++        ---------", "        ,,,,,,,,,,,,,,,,,,  +++++++++++++++++++        ---------", "        ,,,,,,,,,,,,,,,,,,  +++++..............        ---------", "        //////////////////  ...................        ---------", "        //////////////////  ...................        000000000", "        //////////////////  ...................        000000000", "        //////////////////  ...................        000000000", "        //////////////////   ..................        000000000", "        //////////////////   .......11111111111        000000000", "        222222222222222222   111111111111111111        000000000", "         22222222222222222   111111111111111111        333333333", "         22222222222222222   111111111111111111        333333333", "         222222222222222222  111111111111111111        333333333", "         222222222222222222  111111111111111111        333333333", "         222222222222222222  111111114444444444        333333333", "         555555555555555555  444444444444444444        333333333", "         555555555555555555  444444444444444444        666666666", "         555555555555555555  444444444444444444        666666666", "         555555555555555555  444444444444444444        666666666", "         555555555555555555  444444444444444444        666666666", "         555555555555555555  444444444477777777        666666666", "         888888888888888888  777777777777777777        666666666", "         888888888888888888  7777777777777777777        99999999", "         888888888888888888  7777777777777777777        99999999", "         888888888888888888  7777777777777777777        99999999", "         888888888888888888  7777777777777777777        99999999", ":        888888888888888888  777777777777;;;;;;;        99999999", ":        888888888888888888  ;;;;;;;;;;;;;;;;;;;        99999999", ":        888888888888888888  ;;;;;;;;;;;;;;;;;;;        999<<<<<", ":        888888888888888888   ;;;;;;;;;;;;;;;;;;        <<<<<<<<", ":        888888888888888888   ;;;;;;;;;;;;;;;;;;        <<<<<<<<", ":         88888888888888888   ;;;;;;;;;;;;;;;;;;        <<<<<<<<", ":         888888888888888888  ;;;;;;;;;;;;;=====        <<<<<<<<", ":         >>>>>>>>>>>>>>>>>>  ==================        <<<<<<<<", ":         >>>>>>>>>>>>>>>>>>  ==================        <<<<????", ":         >>>>>>>>>>>>>>>>>>  ==================        ????????", ":         >>>>>>>>>>>>>>>>>>  ==================        ????????", ":         >>>>>>>>>>>>>>>>>>  ==================        ????????", ":         >>>>>>>>>>>>>>>>>>  ==============@@@@        ????????", ":         AAAAAAAAAAAAAAAAAA  @@@@@@@@@@@@@@@@@@        ????????", ":         AAAAAAAAAAAAAAAAAA  @@@@@@@@@@@@@@@@@@        ?????BBB", ":         AAAAAAAAAAAAAAAAAA  @@@@@@@@@@@@@@@@@@        BBBBBBBB", ":         AAAAAAAAAAAAAAAAAA  @@@@@@@@@@@@@@@@@@        BBBBBBBB", ":         AAAAAAAAAAAAAAAAAA  @@@@@@@@@@@@@@@@@@         BBBBBBB"]}