{"keys": ["42765", "", "42793", "42849", "42850", "42794", "42736", "42795", "42737", "42851", "42796", "42738", "42797", "42739", "42852", "42798", "42740", "42853", "42799", "42741", "42854", "42800", "42742", "42855", "42801", "42743", "42744", "42856", "42802"], "data": {"42854": {"propaddres": 19335, "proaddress": "19335 PRAIRIE", "parcelnumb": "16023122.", "fid": 42854, "ownername1": "JONES, M L & W G JONES"}, "42855": {"propaddres": 19325, "proaddress": "19325 PRAIRIE", "parcelnumb": "16023123.", "fid": 42855, "ownername1": "MOSS, THADDEUS W"}, "42856": {"propaddres": 19315, "proaddress": "19315 PRAIRIE", "parcelnumb": "16023124.", "fid": 42856, "ownername1": "ACE INVESTMENT GROUP LLC"}, "42850": {"propaddres": 19375, "proaddress": "19375 PRAIRIE", "parcelnumb": "16023118.", "fid": 42850, "ownername1": "LEWIS, DAVID & VICKIE"}, "42795": {"propaddres": 19372, "proaddress": "19372 SAN JUAN", "parcelnumb": "16025688.", "fid": 42795, "ownername1": "CLARK, SHEDRICK & S"}, "42852": {"propaddres": 19353, "proaddress": "19353 PRAIRIE", "parcelnumb": "16023120.", "fid": 42852, "ownername1": "BENNETT, GEORGE"}, "42853": {"propaddres": 19345, "proaddress": "19345 PRAIRIE", "parcelnumb": "16023121.", "fid": 42853, "ownername1": "CHAMBLISS, LARRY & DEMETTA"}, "42851": {"propaddres": 19365, "proaddress": "19365 PRAIRIE", "parcelnumb": "16023119.", "fid": 42851, "ownername1": "LEWIS, FELIPE"}, "42765": {"propaddres": 3189, "proaddress": "3189 W OUTER DRIVE", "parcelnumb": "16008870.", "fid": 42765, "ownername1": "LAW, JOYCE C"}, "42744": {"propaddres": 19319, "proaddress": "19319 SAN JUAN", "parcelnumb": "16025835.", "fid": 42744, "ownername1": "INFINITI HOMES INTERNATIONAL INC"}, "42740": {"propaddres": 19353, "proaddress": "19353 SAN JUAN", "parcelnumb": "16025831.", "fid": 42740, "ownername1": "WOODARD, LANE"}, "42741": {"propaddres": 19341, "proaddress": "19341 SAN JUAN", "parcelnumb": "16025832.", "fid": 42741, "ownername1": "FANNIE MAE"}, "42742": {"propaddres": 19333, "proaddress": "19333 SAN JUAN", "parcelnumb": "16025833.", "fid": 42742, "ownername1": "JENKINS, ELOISE"}, "42743": {"propaddres": 19325, "proaddress": "19325 SAN JUAN", "parcelnumb": "16025834.", "fid": 42743, "ownername1": "PAYNE, EUNICE S"}, "42802": {"propaddres": 19312, "proaddress": "19312 SAN JUAN", "parcelnumb": "16025681.", "fid": 42802, "ownername1": "GARRISON, ARTHUR L SR"}, "42801": {"propaddres": 19324, "proaddress": "19324 SAN JUAN", "parcelnumb": "16025682.", "fid": 42801, "ownername1": "SMITH, SANDRA R"}, "42800": {"propaddres": 19334, "proaddress": "19334 SAN JUAN", "parcelnumb": "16025683.", "fid": 42800, "ownername1": "CLEAVER, CLEON & ORR, MAYA"}, "42799": {"propaddres": 19344, "proaddress": "19344 SAN JUAN", "parcelnumb": "16025684.", "fid": 42799, "ownername1": "DUDLEY, DAVAN"}, "42798": {"propaddres": 19352, "proaddress": "19352 SAN JUAN", "parcelnumb": "16025685.", "fid": 42798, "ownername1": "PERSON, REGINALD"}, "42797": {"propaddres": 19360, "proaddress": "19360 SAN JUAN", "parcelnumb": "16025686.", "fid": 42797, "ownername1": "SHEARER, DOLLIE M"}, "42796": {"propaddres": 19366, "proaddress": "19366 SAN JUAN", "parcelnumb": "16025687.", "fid": 42796, "ownername1": "SHEARER, HAYWARD S"}, "42849": {"propaddres": 19383, "proaddress": "19383 PRAIRIE", "parcelnumb": "16023117.", "fid": 42849, "ownername1": "TYUS, L."}, "42794": {"propaddres": 19376, "proaddress": "19376 SAN JUAN", "parcelnumb": "16025689.", "fid": 42794, "ownername1": "CLARK, SHEDRICK"}, "42793": {"propaddres": 19390, "proaddress": "19390 SAN JUAN", "parcelnumb": "16008869.", "fid": 42793, "ownername1": "GILLIAM EMMA JEAN"}, "42739": {"propaddres": 19359, "proaddress": "19359 SAN JUAN", "parcelnumb": "16025830.", "fid": 42739, "ownername1": "HOWARD, HARRY A &  DENISE L"}, "42738": {"propaddres": 19367, "proaddress": "19367 SAN JUAN", "parcelnumb": "16025829.", "fid": 42738, "ownername1": "PERSON, REGINALD"}, "42737": {"propaddres": 19373, "proaddress": "19373 SAN JUAN", "parcelnumb": "16025828.", "fid": 42737, "ownername1": "JONES, GOLDEN JR"}, "42736": {"propaddres": 19379, "proaddress": "19379 SAN JUAN", "parcelnumb": "16025827.", "fid": 42736, "ownername1": "WOODS, EVON NORWOOD & SMITH, JAMES"}}, "grid": ["       !!!!!!!!!!!######!!!!!!!!!!!!!!!!$$$$$$$$$$$$$$$$$$$$$!!!", "!!!!!!!!!!!!!!!!!!!!!!!!!!!!!!!!!!!!!!!!$$$$$$$$$$$$$$$$$$$$$!!!", "!!!!!!!!!!!!!!!!!!!!!!!!!!!!!!!!!!!!!!!!$$$$$$%%%%%%%%%%%%%%%%!!", "!!!!!!!!!!!!!!!!!&&&&&&&&&&&&&&&&&&&&&&!!%%%%%%%%%%%%%%%%%%%%%!!", "'''''''!!!!!!!!!!&&&&&&&&&&&&&&&&&&&&&&!!%%%%%%%%%%%%%%%%%%%%%!!", "'''''''!!!!!!!!!!&&&&&&&&&&&&&&&&&&&&&&!!%%%%%%%%%%%%%%%%%%%%%!!", "'''''''!!!!!!!!!!&&&&&&&&&&&&&&&&&&&&&&!!%%%%%%%%%%%%%%%%%%%%%!!", "'''''''!!!!!!!!!!!&&&&&&&&&&&&&&&&&&&&&!!%%%%%%%%%%%%%%%%%%%%%!!", "'''''''!!!!!!!!!!!&&&&&&&&&&&&&&&&&&&&&!!%%%%%%%%%%%%%%%%%%%%%!!", "'''''''!!!!!!!!!!!(((((((((((((((((((((!!%%%%%%%%%%%%%%%%%%%%%!!", ")))))))!!!!!!!!!!!(((((((((((((((((((((!!%%%%%%%%%%%%%%%%%%%%%!!", ")))))))!!!!!!!!!!!(((((((((((((((((((((!!%%%%%%%%%%%%%%%%%%%%%!!", ")))))))!!!!!!!!!!!(((((((((((((((((((((!!%%%%%%%%%%%%%%%%%%%%%!!", ")))))))!!!!!!!!!!!(((((((((((((((((((((!!%%%%%%%%%%%%%%%%%%%%%!!", ")))))))!!!!!!!!!!!(((((((((((((((((((((!!%%*******************!!", ")))))))!!!!!!!!!!!+++++++++++++++++++++!!*********************!!", ",,,,,,,!!!!!!!!!!!+++++++++++++++++++++!!*********************!!", ",,,,,,,!!!!!!!!!!!+++++++++++++++++++++!!!********************!!", ",,,,,,,!!!!!!!!!!!+++++++++++++++++++++!!!********************!!", ",,,,,,,!!!!!!!!!!!+++++++++++++++++++++!!!********************!!", ",,,,,,,!!!!!!!!!!!+++++++++++++++++++++!!!********************!!", ",,,,,,,!!!!!!!!!!!---------------------!!!********************!!", ".......!!!!!!!!!!!---------------------!!!********************!!", ".......!!!!!!!!!!!---------------------!!!////////////////////!!", ".......!!!!!!!!!!!---------------------!!!////////////////////!!", ".......!!!!!!!!!!!---------------------!!!////////////////////!!", ".......!!!!!!!!!!!---------------------!!!////////////////////!!", "........!!!!!!!!!!000000000000000000000!!!////////////////////!!", "11111111!!!!!!!!!!000000000000000000000!!!////////////////////!!", "11111111!!!!!!!!!!000000000000000000000!!!////////////////////!!", "11111111!!!!!!!!!!000000000000000000000!!!////////////////////!!", "11111111!!!!!!!!!!000000000000000000000!!!////////////////////!!", "11111111!!!!!!!!!!000000000000000000000!!!22222222222222222222!!", "11111111!!!!!!!!!!000333333333333333333!!!22222222222222222222!!", "11111111!!!!!!!!!!333333333333333333333!!!22222222222222222222!!", "11111111!!!!!!!!!!333333333333333333333!!!22222222222222222222!!", "11111111!!!!!!!!!!333333333333333333333!!!22222222222222222222!!", "44444444!!!!!!!!!!333333333333333333333!!!22222222222222222222!!", "44444444!!!!!!!!!!333333333333333333333!!!22222222222222222222!!", "44444444!!!!!!!!!!333333333333333333333!!!22222222222222222222!!", "44444444!!!!!!!!!!333333333333333333333!!!22222222222222222555!!", "44444444!!!!!!!!!!333333333333333333333!!!55555555555555555555!!", "44444444!!!!!!!!!!333333666666666666666!!!55555555555555555555!!", "44444444!!!!!!!!!!666666666666666666666!!!55555555555555555555!!", "44444444!!!!!!!!!!666666666666666666666!!!55555555555555555555!!", "44444444!!!!!!!!!!666666666666666666666!!!55555555555555555555!!", "77777777!!!!!!!!!!666666666666666666666!!!55555555555555555555!!", "77777777!!!!!!!!!!666666666666666666666!!!55555555555555555555!!", "77777777!!!!!!!!!!666666666666666666666!!!55555555555555555555!!", "77777777!!!!!!!!!!666666666666666666666!!!55555555555588888888!!", "77777777!!!!!!!!!!666666666666666666666!!!88888888888888888888!!", "77777777!!!!!!!!!!666666666999999999999!!!88888888888888888888!!", "::::::::!!!!!!!!!!9999999999999999999999!!88888888888888888888!!", "::::::::!!!!!!!!!!9999999999999999999999!!88888888888888888888!!", "::::::::!!!!!!!!!!9999999999999999999999!!88888888888888888888!!", "::::::::!!!!!!!!!!9999999999999999999999!!88888888888888888888!!", "::::::::!!!!!!!!!!9999999999999999999999!!88888888888888888888!!", "::::::::!!!!!!!!!!9999999999999999999999!!88888888888888888888!!", ";;;;;;;;!!!!!!!!!!9999999999999999999999!!88888888<<<<<<<<<<<<!!", ";;;;;;;;!!!!!!!!!!9999999999999999999999!!<<<<<<<<<<<<<<<<<<<<!!", ";;;;;;;;!!!!!!!!!!999999999999==========!!<<<<<<<<<<<<<<<<<<<<<!", ";;;;;;;;!!!!!!!!!!======================!!<<<<<<<<<<<<<<<<<<<<<!", ";;;;;;;;!!!!!!!!!!======================!!<<<<<<<<<<<<<<<<<<<<<!", ";;;;;;;;!!!!!!!!!!======================!!<<<<<<<<<<<<<<<<<<<<<!"]}