{"keys": ["315788", "315802", "315829", "", "332893", "332924", "332937", "332950", "332963", "332976", "332990", "333003", "333017", "333030", "333043", "332894", "315830", "332895", "315831", "332896", "315789", "332897", "332925", "332938", "332951", "332964", "332977", "332991", "333004", "333018", "333031", "333044", "315832", "332898", "315833", "332899", "333005", "333019", "333032", "315791", "315804", "315837", "332900", "332926", "332940", "332952", "332965", "332979", "332992", "315839", "332901", "315841", "332902", "333033", "315793", "315805", "332927", "332941", "332954", "332967", "332980", "332993", "333006", "333020", "315842", "332903", "315843", "332904", "333034", "315795", "315807", "315834", "332905", "332928", "332942", "332955", "332968", "332982", "332995", "333007", "333021", "315835", "332906", "315836", "332907", "315796", "315808", "332996", "333009", "333023", "333036", "332908", "332929", "332943", "332956", "332969", "332983", "315838"], "data": {"333033": {"propaddres": 15285, "proaddress": "15285 YOUNG", "parcelnumb": "21015982.", "fid": 333033, "ownername1": "MITCHELL, RAMONA"}, "332929": {"propaddres": 15225, "proaddress": "15225 ROCHELLE", "parcelnumb": "21015411.", "fid": 332929, "ownername1": "THOMPSON, LEMUEL"}, "332928": {"propaddres": 15220, "proaddress": "15220 YOUNG", "parcelnumb": "21015438.", "fid": 332928, "ownername1": "BATES, WANDA"}, "332925": {"propaddres": 15221, "proaddress": "15221 HAZELRIDGE", "parcelnumb": "21016241.", "fid": 332925, "ownername1": "DILWORTH, ROBIN"}, "332924": {"propaddres": 15222, "proaddress": "15222 CEDARGROVE", "parcelnumb": "21016286.", "fid": 332924, "ownername1": "MI LAND BANK FAST TRACK AUTH"}, "332927": {"propaddres": 15223, "proaddress": "15223 YOUNG", "parcelnumb": "21015974.", "fid": 332927, "ownername1": "COMMUNITY MORTGAGE SERVICES"}, "332926": {"propaddres": 15220, "proaddress": "15220 HAZELRIDGE", "parcelnumb": "21016008.", "fid": 332926, "ownername1": "RIVERS, AARON & MARY"}, "333009": {"propaddres": 15269, "proaddress": "15269 ROCHELLE", "parcelnumb": "21015417.", "fid": 333009, "ownername1": "WEAVER, GERRY SR"}, "333003": {"propaddres": 15268, "proaddress": "15268 CEDARGROVE", "parcelnumb": "21016280.", "fid": 333003, "ownername1": "CLARK, LESTER"}, "333005": {"propaddres": 15270, "proaddress": "15270 HAZELRIDGE", "parcelnumb": "21016002.", "fid": 333005, "ownername1": "KEMP, DAVID C"}, "333004": {"propaddres": 15271, "proaddress": "15271 HAZELRIDGE", "parcelnumb": "21016247.", "fid": 333004, "ownername1": "CUMBERLANDER, DEAILO & PARKER, CURI"}, "333007": {"propaddres": 15270, "proaddress": "15270 YOUNG", "parcelnumb": "21015432.", "fid": 333007, "ownername1": "WALKER, DAVID"}, "333006": {"propaddres": 15271, "proaddress": "15271 YOUNG", "parcelnumb": "21015980.", "fid": 333006, "ownername1": "HILLBUBB ACQUISITIONS LLC"}, "333034": {"propaddres": 15284, "proaddress": "15284 YOUNG", "parcelnumb": "21015430.", "fid": 333034, "ownername1": "AYEGBENI, PETER"}, "333036": {"propaddres": 15285, "proaddress": "15285 ROCHELLE", "parcelnumb": "21015419.", "fid": 333036, "ownername1": "SILVER, ELIZABETH M"}, "333030": {"propaddres": 15286, "proaddress": "15286 CEDARGROVE", "parcelnumb": "21016278.", "fid": 333030, "ownername1": "DETROIT PROGRESS FUND II, LLC"}, "333031": {"propaddres": 15285, "proaddress": "15285 HAZELRIDGE", "parcelnumb": "21016249.", "fid": 333031, "ownername1": "HENDRIX, RAYMOND"}, "333032": {"propaddres": 15284, "proaddress": "15284 HAZELRIDGE", "parcelnumb": "21015999-6000", "fid": 333032, "ownername1": "BURNETT, YVONNE E TRUST"}, "332995": {"propaddres": 15262, "proaddress": "15262 YOUNG", "parcelnumb": "21015433.", "fid": 332995, "ownername1": "WILSON, SALINA"}, "332903": {"propaddres": 12710, "proaddress": "12710 HAYES", "parcelnumb": "21056476-8", "fid": 332903, "ownername1": "SUPER REALITY LLC"}, "332902": {"propaddres": 12720, "proaddress": "12720 HAYES", "parcelnumb": "21056479.", "fid": 332902, "ownername1": "BASS, JOHNNY"}, "332901": {"propaddres": 12730, "proaddress": "12730 HAYES", "parcelnumb": "21056480-2", "fid": 332901, "ownername1": "BOSS, JOHN"}, "332900": {"propaddres": 12740, "proaddress": "12740 HAYES", "parcelnumb": "21056483-4", "fid": 332900, "ownername1": "JACKSON, LAVELL"}, "332907": {"propaddres": 12622, "proaddress": "12622 HAYES", "parcelnumb": "21056468.", "fid": 332907, "ownername1": "BROWN, KESHA"}, "332906": {"propaddres": 12630, "proaddress": "12630 HAYES", "parcelnumb": "21056469-71", "fid": 332906, "ownername1": "GORDON, KESHA M"}, "332905": {"propaddres": 12640, "proaddress": "12640 HAYES", "parcelnumb": "21056472-3", "fid": 332905, "ownername1": "DEANS, WYNTER D"}, "332904": {"propaddres": 12700, "proaddress": "12700 HAYES", "parcelnumb": "21056474-5", "fid": 332904, "ownername1": "LOEW, CLEASTER"}, "332908": {"propaddres": 12612, "proaddress": "12612 HAYES", "parcelnumb": "21056466-7", "fid": 332908, "ownername1": "JOHNSON, GERALD & CHERYL"}, "333023": {"propaddres": 15279, "proaddress": "15279 ROCHELLE", "parcelnumb": "21015418.", "fid": 333023, "ownername1": "BARRON, JOHN & LAURA"}, "333021": {"propaddres": 15276, "proaddress": "15276 YOUNG", "parcelnumb": "21015431.", "fid": 333021, "ownername1": "WENDELL, RUSSELL"}, "333020": {"propaddres": 15277, "proaddress": "15277 YOUNG", "parcelnumb": "21015981.", "fid": 333020, "ownername1": "NATIONSTAR MORTGAGE  LLC"}, "315802": {"propaddres": 15090, "proaddress": "15090 CEDARGROVE", "parcelnumb": "21016287.", "fid": 315802, "ownername1": "CITY OF DETROIT-P&DD"}, "315805": {"propaddres": 15091, "proaddress": "15091 YOUNG", "parcelnumb": "21015973.", "fid": 315805, "ownername1": "DOUGHRITY, SANDRA"}, "315804": {"propaddres": 15090, "proaddress": "15090 HAZELRIDGE", "parcelnumb": "21016009.", "fid": 315804, "ownername1": "CHATMAN, RANDOLPH L AND DEBBIE"}, "315807": {"propaddres": 15090, "proaddress": "15090 YOUNG", "parcelnumb": "21015439.", "fid": 315807, "ownername1": "DAVIE, KAREN"}, "315808": {"propaddres": 15091, "proaddress": "15091 ROCHELLE", "parcelnumb": "21015410.", "fid": 315808, "ownername1": "BROWN, IRENE"}, "332996": {"propaddres": 15263, "proaddress": "15263 ROCHELLE", "parcelnumb": "21015416.", "fid": 332996, "ownername1": "ASR SOLUTIONS LLC"}, "332990": {"propaddres": 15260, "proaddress": "15260 CEDARGROVE", "parcelnumb": "21016281.", "fid": 332990, "ownername1": "YARBROUGH, CARLA P"}, "332991": {"propaddres": 15261, "proaddress": "15261 HAZELRIDGE", "parcelnumb": "21016246.", "fid": 332991, "ownername1": "GAMBRELL, DANETTE"}, "332992": {"propaddres": 15260, "proaddress": "15260 HAZELRIDGE", "parcelnumb": "21016003.", "fid": 332992, "ownername1": "BROOKS, ADELLA"}, "332993": {"propaddres": 15261, "proaddress": "15261 YOUNG", "parcelnumb": "21015979.", "fid": 332993, "ownername1": "DIXON, ANTHONY & LINDA"}, "315837": {"propaddres": 12743, "proaddress": "12743 HAYES", "parcelnumb": "21056638-9", "fid": 315837, "ownername1": "KEYSTONE ENT INC"}, "332976": {"propaddres": 15254, "proaddress": "15254 CEDARGROVE", "parcelnumb": "21016282.", "fid": 332976, "ownername1": "HARRIS, DANNY"}, "332977": {"propaddres": 15255, "proaddress": "15255 HAZELRIDGE", "parcelnumb": "21016245.", "fid": 332977, "ownername1": "JPMORGAN CHASE BANK"}, "332979": {"propaddres": 15252, "proaddress": "15252 HAZELRIDGE", "parcelnumb": "21016004.", "fid": 332979, "ownername1": "CURTIS, PATRICIA"}, "315788": {"propaddres": 15082, "proaddress": "15082 CEDARGROVE", "parcelnumb": "21016288.", "fid": 315788, "ownername1": "CITY OF DETROIT"}, "315789": {"propaddres": 15087, "proaddress": "15087 HAZELRIDGE", "parcelnumb": "21016239-40", "fid": 315789, "ownername1": "HUD"}, "315838": {"propaddres": 12611, "proaddress": "12611 HAYES", "parcelnumb": "21056656-8", "fid": 315838, "ownername1": "GRAY, LULA B"}, "315839": {"propaddres": 12731, "proaddress": "12731 HAYES", "parcelnumb": "21056640-2", "fid": 315839, "ownername1": "REID, TISA"}, "332983": {"propaddres": 15255, "proaddress": "15255 ROCHELLE", "parcelnumb": "21015415.", "fid": 332983, "ownername1": "STUDINGER, LEOPOLD"}, "332982": {"propaddres": 15254, "proaddress": "15254 YOUNG", "parcelnumb": "21015434.", "fid": 332982, "ownername1": "WILDER, LANITA ANN"}, "315836": {"propaddres": 12621, "proaddress": "12621 HAYES", "parcelnumb": "21056654-5", "fid": 315836, "ownername1": "ROBERSON, PATRICIA ANN"}, "332980": {"propaddres": 15255, "proaddress": "15255 YOUNG", "parcelnumb": "21015978.", "fid": 332980, "ownername1": "CRAIGHEAD, EARNELL"}, "315830": {"propaddres": 12831, "proaddress": "12831 HAYES", "parcelnumb": "21056629-31", "fid": 315830, "ownername1": "BROOKS, LAVETTA"}, "315831": {"propaddres": 12821, "proaddress": "12821 HAYES", "parcelnumb": "21056632-3", "fid": 315831, "ownername1": "JKAG PROPERTIES LLC"}, "315832": {"propaddres": 12809, "proaddress": "12809 HAYES", "parcelnumb": "21056634-5", "fid": 315832, "ownername1": "BROOKS, LAVETTA"}, "315833": {"propaddres": 12801, "proaddress": "12801 HAYES", "parcelnumb": "21056636-7", "fid": 315833, "ownername1": "DUVALL, WILLIAM"}, "332965": {"propaddres": 15246, "proaddress": "15246 HAZELRIDGE", "parcelnumb": "21016005.", "fid": 332965, "ownername1": "15246 HAZELRIDGE LLC"}, "332964": {"propaddres": 15247, "proaddress": "15247 HAZELRIDGE", "parcelnumb": "21016244.", "fid": 332964, "ownername1": "GEAR, HYLAND T"}, "332967": {"propaddres": 15247, "proaddress": "15247 YOUNG", "parcelnumb": "21015977.", "fid": 332967, "ownername1": "BYRD, DEBORAH E"}, "332963": {"propaddres": 15246, "proaddress": "15246 CEDARGROVE", "parcelnumb": "21016283.", "fid": 332963, "ownername1": "15246 CEDARGROVE, LLC"}, "332969": {"propaddres": 15247, "proaddress": "15247 ROCHELLE", "parcelnumb": "21015414.", "fid": 332969, "ownername1": "USSERY, GERALD E"}, "332968": {"propaddres": 15246, "proaddress": "15246 YOUNG", "parcelnumb": "21015435.", "fid": 332968, "ownername1": "LAKEMOUNT CORPORATION"}, "333044": {"propaddres": 15295, "proaddress": "15295 HAZELRIDGE", "parcelnumb": "21016250.", "fid": 333044, "ownername1": "HOME SOLUTIONS PARTNERS IV REO LLC"}, "333043": {"propaddres": 15292, "proaddress": "15292 CEDARGROVE", "parcelnumb": "21016277.", "fid": 333043, "ownername1": "LUCKETT, THEODORE"}, "315795": {"propaddres": 15082, "proaddress": "15082 YOUNG", "parcelnumb": "21015440.", "fid": 315795, "ownername1": "GRIFFIN, JOHN JR"}, "315796": {"propaddres": 15083, "proaddress": "15083 ROCHELLE", "parcelnumb": "21015409.", "fid": 315796, "ownername1": "NASH, EMILY JEWEL"}, "315791": {"propaddres": 15082, "proaddress": "15082 HAZELRIDGE", "parcelnumb": "21016010.", "fid": 315791, "ownername1": "CHATMAN, RANDOLPH L & DEBBIE"}, "315793": {"propaddres": 15081, "proaddress": "15081 YOUNG", "parcelnumb": "21015972.", "fid": 315793, "ownername1": "CARMICHAEL, BRIAN"}, "315829": {"propaddres": 12841, "proaddress": "12841 HAYES", "parcelnumb": "21056626-8", "fid": 315829, "ownername1": "JONES, JAUNAE G"}, "315841": {"propaddres": 12721, "proaddress": "12721 HAYES", "parcelnumb": "21056643-4", "fid": 315841, "ownername1": "MAYE, JAMES"}, "315843": {"propaddres": 12701, "proaddress": "12701 HAYES", "parcelnumb": "21056648.", "fid": 315843, "ownername1": "DEUTSCHE BANK NATIONAL"}, "315842": {"propaddres": 12711, "proaddress": "12711 HAYES", "parcelnumb": "21056645-7", "fid": 315842, "ownername1": "BROCK, PATRICIA ANN"}, "332950": {"propaddres": 15238, "proaddress": "15238 CEDARGROVE", "parcelnumb": "21016284.", "fid": 332950, "ownername1": "JAMISON, SHIRLEY"}, "332951": {"propaddres": 15239, "proaddress": "15239 HAZELRIDGE", "parcelnumb": "21016243.", "fid": 332951, "ownername1": "BOUNDS, JIMMIE"}, "332952": {"propaddres": 15240, "proaddress": "15240 HAZELRIDGE", "parcelnumb": "21016006.", "fid": 332952, "ownername1": "WOODSON, MELVIN II"}, "332954": {"propaddres": 15241, "proaddress": "15241 YOUNG", "parcelnumb": "21015976.", "fid": 332954, "ownername1": "WILLIAMS, ROBERT"}, "332955": {"propaddres": 15240, "proaddress": "15240 YOUNG", "parcelnumb": "21015436.", "fid": 332955, "ownername1": "BRADFORD, TERRENCE"}, "332956": {"propaddres": 15237, "proaddress": "15237 ROCHELLE", "parcelnumb": "21015413.", "fid": 332956, "ownername1": "LAKEMOUNT CORPORATION"}, "332943": {"propaddres": 15231, "proaddress": "15231 ROCHELLE", "parcelnumb": "21015412.", "fid": 332943, "ownername1": "FEW, DEMETRIUS L & ROSE, LATASHIA Y"}, "332942": {"propaddres": 15230, "proaddress": "15230 YOUNG", "parcelnumb": "21015437.", "fid": 332942, "ownername1": "BATES, WANDA"}, "332941": {"propaddres": 15231, "proaddress": "15231 YOUNG", "parcelnumb": "21015975.", "fid": 332941, "ownername1": "TURNER, LEON C"}, "332940": {"propaddres": 15230, "proaddress": "15230 HAZELRIDGE", "parcelnumb": "21016007.", "fid": 332940, "ownername1": "KING, CALVIN"}, "332893": {"propaddres": 12846, "proaddress": "12846 HAYES", "parcelnumb": "21056495.", "fid": 332893, "ownername1": "JOHNSON, MICHAEL T & TERESA"}, "332895": {"propaddres": 12830, "proaddress": "12830 HAYES", "parcelnumb": "21056492.", "fid": 332895, "ownername1": "MOORE, KIZZIE"}, "332894": {"propaddres": 12840, "proaddress": "12840 HAYES", "parcelnumb": "21056493-4", "fid": 332894, "ownername1": "JOHNSON, MICHAEL T & TERESA MARIE"}, "332897": {"propaddres": 12820, "proaddress": "12820 HAYES", "parcelnumb": "21056489.", "fid": 332897, "ownername1": "FUGA, MARK"}, "332896": {"propaddres": 12828, "proaddress": "12828 HAYES", "parcelnumb": "21056490-1", "fid": 332896, "ownername1": "MOORE, KIZZIE COMEAL"}, "332899": {"propaddres": 12800, "proaddress": "12800 HAYES", "parcelnumb": "21056485-6", "fid": 332899, "ownername1": "HENCE, MARY"}, "332898": {"propaddres": 12814, "proaddress": "12814 HAYES", "parcelnumb": "21056487-8", "fid": 332898, "ownername1": "BERRY, LONNETTA P"}, "315834": {"propaddres": 12641, "proaddress": "12641 HAYES", "parcelnumb": "21056649-50", "fid": 315834, "ownername1": "WILLIAMS, FREDY"}, "332938": {"propaddres": 15231, "proaddress": "15231 HAZELRIDGE", "parcelnumb": "21016242.", "fid": 332938, "ownername1": "DILWORTH, ROBIN"}, "315835": {"propaddres": 12631, "proaddress": "12631 HAYES", "parcelnumb": "21056651-3", "fid": 315835, "ownername1": "KINNIE, ANDERSON"}, "332937": {"propaddres": 15230, "proaddress": "15230 CEDARGROVE", "parcelnumb": "21016285.", "fid": 332937, "ownername1": "GANGLEY, TINA M"}, "333018": {"propaddres": 15277, "proaddress": "15277 HAZELRIDGE", "parcelnumb": "21016248.", "fid": 333018, "ownername1": "MOORE, WALTER & JOYCE"}, "333019": {"propaddres": 15276, "proaddress": "15276 HAZELRIDGE", "parcelnumb": "21016001.", "fid": 333019, "ownername1": "HARVILLE, FLORALENE"}, "333017": {"propaddres": 15276, "proaddress": "15276 CEDARGROVE", "parcelnumb": "21016279.", "fid": 333017, "ownername1": "JOHNSON, ANTHONY"}}, "grid": ["  !!!!########$$$$$$$$$$%%%%%%%$$&&&'''((())))***+++,,,,---..../", "  !!!!########$$$$$$$$$$%%%%%%%$$&&&'''((())))***+++,,,,---..../", "  !!!!########$$$$$$$$$$%%%%%%%$$&&&'''((())))***+++,,,,---..../", "  !!!!########$$$$$$$$$$0000000$$&&&'''(((()))***+++,,,,---..../", "  !!!!11111111$$$$$$$$$$0000000$$&&&'''(((()))***+++,,,,---..../", "  !!!!11111111$$$$$$$$$$2222222$$&&&'''(((()))***+++,,,,---..../", "  !!!!11111111$$$$$$$$$$2222222$$&&&'''(((()))***+++,,,,---..../", "  !!!!11111111$$$$$$$$$$2222222$$&&&'''(((()))***+++,,,,---..../", "  !!!!33333333$$$$$$$$$$4444444$$&&&'''(((()))***+++,,,,---..../", "  !!!!33333333$$$$$$$$$$44444444$$$$$$$$$$$$$$$$$$$$$$$$$$$$$$$$", "55555533333333$$$$$$$$$$46666666$7778889999:::;;;<<<====>>>????@", "55555533333333$$$$$$$$$$66666666$7778889999:::;;;<<<====>>>????@", "55555533333333$$$$$$$$$$66666666$7778889999:::;;;<<<====>>>????@", "555555AAAAAAAA$$$$$$$$$$BBBBBBBB$7778889999:::;;;<<<<===>>>????@", "555555AAAAAAAA$$$$$$$$$$BBBBBBBB$7778889999:::;;;<<<<===>>>????@", "555555AAAAAAAA$$$$$$$$$$BBBBBBBB$7778889999:::;;;<<<<===>>>????@", "555555CCCCCCCC$$$$$$$$$$DDDDDDDD$7778889999:::;;;<<<<===>>>????@", "555555CCCCCCCC$$$$$$$$$$DDDDDDDD$7778889999:::;;;<<<<===>>>>???@", "555555CCCCCCCC$$$$$$$$$$DDDDDDDD$7778889999:::;;;<<<<===>>>>???@", "555555CCCCCCCCC$$$$$$$$$DDDDDDDD$7778888999:::;;;<<<<===>>>>???@", "$$$$$$$$$$$$$$$$$$$$$$$$$$$$$$$$$$$$$$$$$$$$$$$$$$$$$$$$$$$$$$$$", "$$$$$$$$$$$$$$$$$$$$$$$$$$$$$$$$$$$$$$$$$$$$$$$$$$$$$$$$$$$$$$$$", "$$$$$$$$$$$$$$$$$$$$$$$$$$$$$$$$$$$$$$$$$$$$$$$$$$$$$$$$$$$$$$$$", "$$$$$$$$$$$$$$$$$$$$$$$$$$$$$$$$$$$$$$$$$$$$$$$$$$$$$$$$$$$$$$$$", "$$$$$$$$$$$$$$$$$$$$$$$$$$$$$$$$$$$$$$$$$$$$$$$$$$$$$$EEEFFFGGGG", "HHIIII$JJJJJJJJ$$$$$$$$$KKKKKKKK$LLLLMMMNNNOOOPPPPQQQEEEFFFFGGGG", "HHHIII$JJJJJJJJ$$$$$$$$$$KKKKKKK$LLLLMMMNNNOOOPPPPQQQEEEFFFFGGGG", "HHHIII$JJJJJJJJ$$$$$$$$$$KKKKKKK$LLLLMMMNNNOOOPPPPQQQEEEFFFFGGGG", "HHHIII$JRRRRRRR$$$$$$$$$$KKKKKKK$LLLLMMMNNNOOOPPPPQQQEEEEFFFGGGG", "HHHIII$RRRRRRRR$$$$$$$$$$SSSSSSS$LLLLMMMNNNOOOOPPPQQQEEEEFFFGGGG", "HHHIII$RRRRRRRR$$$$$$$$$$SSSSSSS$LLLLMMMNNNOOOOPPPQQQEEEEFFFGGGG", "HHHIII$RRRRRRRR$$$$$$$$$$SSSSSSS$LLLLMMMNNNOOOOPPPQQQEEEEFFFGGGG", "HHHIII$$RRRRRRR$$$$$$$$$$SSSSSSS$$LLLMMMNNNOOOOPPPQQQEEEEFFFGGGG", "HHHIII$$TTTTTTT$$$$$$$$$$UUUUUUU$$LLLMMMNNNOOOOPPPQQQEEEEFFFGGGG", "HHHIII$$TTTTTTT$$$$$$$$$$UUUUUUU$$LLLMMMNNNOOOOPPPQQQEEEEFFFVVVV", "WWWXXX$$TTTTTTT$$$$$$$$$$UUUUUUU$$YYYZZZ[[[]]]]^^^___````aaaVVVV", "WWWXXX$$TTTTTTT$$$$$$$$$$UUUUUUU$$YYYZZZ[[[]]]]^^^___````aaaVVVV", "WWWXXX$$bbbbbbb$$$$$$$$$$ccccccc$$YYYZZZ[[[]]]]^^^___````aaaVVVV", "WWWXXX$$bbbbbbb$$$$$$$$$$ccccccc$$YYYZZZ[[[[]]]^^^___````aaaVVVV", "WWWXXX$$bbbbbbb$$$$$$$$$$ccccccc$$YYYZZZ[[[[]]]^^^___````aaaVVVV", "WWWXXX$$bbbbbbb$$$$$$$$$$ccccccc$$YYYZZZ[[[[]]]^^^___````aaaVVVV", "WWWXXX$$ddddddd$$$$$$$$$$eeeeeee$$YYYZZZ[[[[]]]^^^___````aaaVVVV", "WWWXXX$$ddddddd$$$$$$$$$$eeeeeee$$YYYZZZ[[[[]]]^^^___````aaaVVVV", "WWWXXX$$ddddddd$$$$$$$$$$eeeeeee$$YYYZZZ[[[[]]]^^^___````aaaVVVV", "WWWXXX$$ddddddd$$$$$$$$$$eeeeeeee$YYYZZZ[[[[]]]^^^___````aaaVVVV", "$$$$$$$$$$$$$$$$$$$$$$$$$eee$$$$$$$$$$$$$$$$$$$$$$$$$$$$$$$$$$$$", "$$$$$$$$$$$$$$$$$$$$$$$$$$$$$$$$$$$$$$$$$$$$$$$$$$$$$$$$$$$$$$$$", "$$$$$$$$$$$$$$$$$$$$$$$$$$$$$$$$$$$$$$$$$$$$$$$$$$$$$$$$$$$$$$$$", "$$$$$$$$$$$$$$$$$$$$$$$$$$$$$$$$$$$$$$$$$$$$$$$$$$$$$$$$$$$$$$$$", "$$$$$$$$$$$$$$$$$$$$$$$$$$$$$$$$$$$$$$$$$$$$$$$$$$$$$$$$$$$$$$$f", "ggghhhhiiiiiiii$$$$$$$$$$jjjjjjjj$kkklllmmmmnnnooopppqqqqrrrffff", "ggghhhhiiiiiiii$$$$$$$$$$jjjjjjjj$kkklllmmmmnnnoooppppqqqrrrffff", "ggghhhhiiiiiiii$$$$$$$$$$jjjjjjjj$kkklllmmmmnnnoooppppqqqrrrffff", "ggghhhhiiiiiiii$$$$$$$$$$jjjjjjjj$kkklllmmmmnnnoooppppqqqrrrffff", "ggghhhhssssssss$$$$$$$$$$tttttttt$kkklllmmmmnnnoooppppqqqrrrrfff", "ggghhhhssssssss$$$$$$$$$$tttttttt$kkkllllmmmnnnoooppppqqqrrrrfff", "ggghhhhssssssss$$$$$$$$$$tttttttt$kkkllllmmmnnnoooppppqqqrrrrfff", "ggghhhhsssssssss$$$$$$$$$tttttttt$kkkllllmmmnnnoooppppqqqrrrrfff", "ggghhhhsssuuuuuu$$$$$$$$$vvvvvvvv$kkkllllmmmnnnoooppppqqqrrrrfff", "ggghhhhuuuuuuuuu$$$$$$$$$vvvvvvvv$kkkllllmmm$$$$$$$$$$$$$$$$$$$$", "wwwxxxxuuuuuuuuu$$$$$$$$$vvvvvvvv$$$$$$$$$$$$$$$$$$$$yzzz{{{{|||", "wwwxxxxuuuuuuuuu$$$$$$$$$$}}}}}}}$~~~\u007f\u007f\u007f\u007f\u0080\u0080\u0080\u0081\u0081\u0081\u0082\u0082\u0082yyyyzzz{{{{|||", "wwwxxxxuuuuuuuuu$$$$$$$$$$}}}}}}}$~~~\u007f\u007f\u007f\u007f\u0080\u0080\u0080\u0081\u0081\u0081\u0082\u0082\u0082yyyyzzz{{{{|||", "wwwxxxx\u0083\u0083\u0083\u0083\u0083\u0083\u0083\u0083\u0083$$$$$$$$$$}}}}}}}$~~~\u007f\u007f\u007f\u007f\u0080\u0080\u0080\u0081\u0081\u0081\u0082\u0082\u0082yyyyzzz{{{{|||"]}