{"keys": ["343907", "343919", "343933", "343943", "", "343966", "343992", "344013", "343932", "343896", "343918", "343895", "352771", "352762", "352752", "352742", "352734", "352715", "352768", "352759", "352750", "352709", "352740", "352704", "352733", "352696", "352725", "352691", "352719", "352713", "352684", "352707"], "data": {"343895": {"propaddres": 3300, "proaddress": "3300 W DAVISON", "parcelnumb": "12004492-3", "fid": 343895, "ownername1": "HARRIS, LEVOLL JR"}, "343896": {"propaddres": 3295, "proaddress": "3295 CLEMENTS", "parcelnumb": "12004552.", "fid": 343896, "ownername1": "REID, JOSEPH & CAROLYN"}, "352733": {"propaddres": 3274, "proaddress": "3274 WAVERLY", "parcelnumb": "12004414.", "fid": 352733, "ownername1": "HOWARD, TANSY"}, "352719": {"propaddres": 3286, "proaddress": "3286 WAVERLY", "parcelnumb": "12004412.", "fid": 352719, "ownername1": "DANIELS, JESSIE M"}, "352734": {"propaddres": 3279, "proaddress": "3279 W DAVISON", "parcelnumb": "12004467.", "fid": 352734, "ownername1": "KENNEDY, FRANCIE"}, "352715": {"propaddres": 3287, "proaddress": "3287 W DAVISON", "parcelnumb": "12004468-70", "fid": 352715, "ownername1": "KENNEDY, FRANCIE L"}, "352713": {"propaddres": 3294, "proaddress": "3294 WAVERLY", "parcelnumb": "12004411.", "fid": 352713, "ownername1": "CITY OF DETROIT-P&DD"}, "352759": {"propaddres": 3250, "proaddress": "3250 WAVERLY", "parcelnumb": "12004417.", "fid": 352759, "ownername1": "CHASE HOME FINANCE LLC"}, "343943": {"propaddres": 3267, "proaddress": "3267 CLEMENTS", "parcelnumb": "12004548.", "fid": 343943, "ownername1": "HARRIS, CHARLES JR & ANN"}, "352750": {"propaddres": 3260, "proaddress": "3260 WAVERLY", "parcelnumb": "12004416.", "fid": 352750, "ownername1": "BENNETT, DALE & GHAWANA"}, "352752": {"propaddres": 3263, "proaddress": "3263 W DAVISON", "parcelnumb": "12004465.", "fid": 352752, "ownername1": "KENNEDY, FRANCIE L"}, "343907": {"propaddres": 3291, "proaddress": "3291 CLEMENTS", "parcelnumb": "12004551.", "fid": 343907, "ownername1": "STREET, LILLIAN"}, "352771": {"propaddres": 3239, "proaddress": "3239 W DAVISON", "parcelnumb": "12004463.", "fid": 352771, "ownername1": "SALEH, MOHAMED NAGI"}, "352691": {"propaddres": 3315, "proaddress": "3315 W DAVISON", "parcelnumb": "12004474.", "fid": 352691, "ownername1": "KENNEDY, FRANCIE L"}, "343966": {"propaddres": 3260, "proaddress": "3260 W DAVISON", "parcelnumb": "12004496-7", "fid": 343966, "ownername1": "N & A PROPERTY MANAGEMENT  LLC"}, "352696": {"propaddres": 3295, "proaddress": "3295 W DAVISON", "parcelnumb": "12004473.", "fid": 352696, "ownername1": "KENNEDY, J & F KENNEDY  & S WHITNEY"}, "352709": {"propaddres": 3289, "proaddress": "3289 W DAVISON", "parcelnumb": "12004471.", "fid": 352709, "ownername1": "KENNEDY, J & F"}, "352725": {"propaddres": 3280, "proaddress": "3280 WAVERLY", "parcelnumb": "12004413.", "fid": 352725, "ownername1": "HARBOUR PORTFOLIO VII, LP"}, "352742": {"propaddres": 3271, "proaddress": "3271 W DAVISON", "parcelnumb": "12004466.", "fid": 352742, "ownername1": "KENNEDY, FRANCIE"}, "352740": {"propaddres": 3266, "proaddress": "3266 WAVERLY", "parcelnumb": "12004415.", "fid": 352740, "ownername1": "PATTERSON, INGRID"}, "352707": {"propaddres": 3300, "proaddress": "3300 WAVERLY", "parcelnumb": "12004410.", "fid": 352707, "ownername1": "AMDERSON, D"}, "352704": {"propaddres": 3291, "proaddress": "3291 W DAVISON", "parcelnumb": "12004472.", "fid": 352704, "ownername1": "KENNEDY, J & F"}, "343932": {"propaddres": 3274, "proaddress": "3274 W DAVISON", "parcelnumb": "12004495.", "fid": 343932, "ownername1": "N & A PROPERTY MANAGEMENT  LLC"}, "343933": {"propaddres": 3275, "proaddress": "3275 CLEMENTS", "parcelnumb": "12004549.", "fid": 343933, "ownername1": "PARMILL INVESTMENTS, LLC"}, "343918": {"propaddres": 3294, "proaddress": "3294 W DAVISON", "parcelnumb": "12004494.", "fid": 343918, "ownername1": "HARRIS, LEVOLL & BESSIE"}, "343919": {"propaddres": 3281, "proaddress": "3281 CLEMENTS", "parcelnumb": "12004550.", "fid": 343919, "ownername1": "WEIS, BEVERLY"}, "344013": {"propaddres": 3200, "proaddress": "3200 W DAVISON", "parcelnumb": "12004500-02", "fid": 344013, "ownername1": "BURGER KING CORP #10286"}, "352762": {"propaddres": 3247, "proaddress": "3247 W DAVISON", "parcelnumb": "12004464.", "fid": 352762, "ownername1": "KENNEDY, FRANCIE L"}, "343992": {"propaddres": 3246, "proaddress": "3246 W DAVISON", "parcelnumb": "12004498-9", "fid": 343992, "ownername1": "N & A PROPERTY MANAGEMENT  LLC"}, "352684": {"propaddres": 3327, "proaddress": "3327 W DAVISON", "parcelnumb": "12004475-6", "fid": 352684, "ownername1": "MOORE, EDWARD J"}, "352768": {"propaddres": 3244, "proaddress": "3244 WAVERLY", "parcelnumb": "12004418.", "fid": 352768, "ownername1": "JUNIEL, OLA F"}}, "grid": ["     !!!!!!#######$$$%%%%&&&&&&&'''''''''''''(((((((((((((((((((", "     !!!!!!!#######%%%%&&&&&&&&&''''''''''''''((((((((((((((((((", "      !!!!!!#####%%%%&&&&&&&&&&&&'''''''''''''((((((((((((((((((", "      !!!!!!!##%%%%)&&&&&&&&&&&&&''''''''''''''((((((((((((((((%", "       !!!!!!%%%%)))&&&&&&&&&&&&&&'''''''''''''((((((((((((((%%%", "       !!!!%%%%))))))&&&&&&&&&&&&&''''''''''''''(((((((((((%%%%%", "*       !%%%%))))))))&&&&&&&&&&&&&&'''''''''''''(((((((((%%%%%%%", "*      %%%%)))))))))))&&&&&&&&&&&&&''''''''''''''((((((%%%%%%%%%", "**   %%%%)))))))))))))&&&&&&&&&&&&&&'''''''''''''((((%%%%%%%%%%%", "** %%%%))))))))))))))))&&&&&&&&&&&&&''''''''''''''(%%%%%%%%%%%%%", "*%%%%))))))))))))))))))&&&&&&&&&&&&&&''''''''''''%%%%%%%%%%%%%%%", "%%%%))))))))))))))))))))&&&&&&&&&&&&&''''''''''%%%%%%%%%%%%%%%%%", "%%++))))))))))))))))))))&&&&&&&&&&&&&&'''''''%%%%%%%%%%%%%%%%%%%", "++++)))))))))))))))))))))&&&&&&&&&&&&&'''''%%%%%%%%%%%%%%%%%%%%%", "+++++))))))))))))))))))))&&&&&&&&&&&&&&''%%%%%%%%%%%%%%%%%%%%%%%", "+++++)))))))))))))))))))))&&&&&&&&&&&&&%%%%%%%%%%%%%%%%%%%%%%%%%", "++++++))))))))))))))))))))&&&&&&&&&&&%%%%%%%%%%%%%%%%%%%%%%%%%%%", "++++++)))))))))))))))))))))&&&&&&&&%%%%%%%%%%%%%%%%%%%%%%%%%%%%%", "+++++++))))))))))))))))))))&&&&&&%%%%%%%%%%%%%%%%%%%%%%%%%%%%%%%", "+++++++)))))))))))))))))))))&&&%%%%%%%%%%%%%%%%%%%%%%%%%%%%%%%%%", ",+++++++))))))))))))))))))))&%%%%%%%%%%%%%%%%%%%%%%%%%%%%%%%%%%%", ",+++++++)))))))))))))))))))%%%%%%%%%%%%%%%%%%%%%%%%%%%%%%%%%%%%%", ",,+++++++))))))))))))))))%%%%%%%%%%%%%%%%%%%%%%%%%%%%%%%%%%%%%%%", ",,+++++++))))))))))))))%%%%%%%%%%%%%%%%%%%%%%%%%%%%%%%%%%%%%%%%%", ",,,+++++++)))))))))))%%%%%%%%%%%%%%%%%%%%%%%%%%%%%%%%%%%%%%%%%%%", ",,,+++++++)))))))))%%%%%%%%%%%%%%%%%%%%%%%%%%%%%%%%%%%%%%%%%%%%%", ",,,,+++++++))))))%%%%%%%%%%%%%%%%%%%%%%%%%%%%%%%%%%%%%%%%%%%%%%-", ",,,,,++++++))))%%%%%%%%%%%%%%%%%%%%%%%%%%%%%%%%%%%%%%%%%%%%%%---", ",,,,,+++++++)%%%%%%%%%%%%%%%%%%%%%%%%%%%%%%%%%%%%%%%%%%%%%%..---", ",,,,,,+++++%%%%%%%%%%%%%%%%%%%%%%%%%%%%%%%%%%%%%%%%%%%%%%.....--", ",,,,,,+++%%%%%%%%%%%%%%%%%%%%%%%%%%%%%%%%%%%%%%%%%%%%%%.......--", ",,,,,,,%%%%%%%%%%%%%%%%%%%%%%%%%%%%%%%%%%%%%%%%%%%%%%///.......-", ",,,,,%%%%%%%%%%%%%%%%%%%%%%%%%%%%%%%%%%%%%%%%%%%%%%/////.......-", ",,,%%%%%%%%%%%%%%%%%%%%%%%%%%%%%%%%%%%%%%%%%%%%%%0///////.......", ",%%%%%%%%%%%%%%%%%%%%%%%%%%%%%%%%%%%%%%%%%%%%%%0000//////.......", "%%%%%%%%%%%%%%%%%%%%%%%%%%%%%%%%%%%%%%%%%%%%%000000///////......", "%%%%%%%%%%%%%%%%%%%%%%%%%%%%%%%%%%%%%%%%%%%11000000///////......", "%%%%%%%%%%%%%%%%%%%%%%%%%%%%%%%%%%%%%%%%%11110000000///////.....", "%%%%%%%%%%%%%%%%%%%%%%%%%%%%%%%%%%%%%%%1111111000000///////...%%", "%%%%%%%%%%%%%%%%%%%%%%%%%%%%%%%%%%%%%2211111110000000///////%%%%", "%%%%%%%%%%%%%%%%%%%%%%%%%%%%%%%%%%%222221111111000000/////%%%%%%", "%%%%%%%%%%%%%%%%%%%%%%%%%%%%%%%%%222222211111110000000//%%%%%%33", "%%%%%%%%%%%%%%%%%%%%%%%%%%%%%%%22222222221111111000000%%%%%%3333", "%%%%%%%%%%%%%%%%%%%%%%%%%%%%%22222222222211111110000%%%%%%444333", "%%%%%%%%%%%%%%%%%%%%%%%%%%%22222222222222211111110%%%%%%44444333", "%%%%%%%%%%%%%%%%%%%%%%%%%22222222222222222111111%%%%%%5444444433", "%%%%%%%%%%%%%%%%%%%%%%622222222222222222222111%%%%%%555444444433", "%%%%%%%%%%%%%%%%%%%%666222222222222222222221%%%%%%55555544444443", "%%%%%%%%%%%%%%%%%%666666222222222222222222%%%%%%7755555544444443", "%%%%%%%%%%%%%%%%886666662222222222222222%%%%%%777755555554444444", "%%%%%%%%%%%%%%888866666662222222222222%%%%%%77777775555554444444", "%%%%%%%%%%%%888888866666622222222222%%%%%%9977777775555555444444", "%%%%%%%%%%::8888888666666622222222%%%%%%999997777777555555444444", "%%%%%%%%:::::8888886666666222222%%%%%%;9999997777777555555544444", "%%%%%%:::::::88888886666666222%%%%%%;;;9999999777777755555544444", "%%%%<<::::::::88888866666662%%%%%%;;;;;;999999777777755555554444", "%%<<<<::::::::888888866666%%%%%%=;;;;;;;999999977777775555554444", "<<<<<<<::::::::888888666%%%%%%====;;;;;;;99999977777775555555444", "<<<<<<<::::::::8888888%%%%%%======;;;;;;;99999997777777555555444", "<<<<<<<<::::::::8888%%%%%%>>=======;;;;;;;9999997777777555555544", "?<<<<<<<::::::::88%%%%%%>>>>>======;;;;;;;9999999777777755555544", "?<<<<<<<<:::::::%%%%%%@>>>>>>=======;;;;;;;9999997777777555555%%", "??<<<<<<<:::::%%%%%%@@@>>>>>>>======;;;;;;;99999997777777555%%%%", "??<<<<<<<<::%%%%%%@@@@@>>>>>>>=======;;;;;;;99999977777775%%%%%%"]}