{"keys": ["356574", "356586", "356599", "356612", "", "356671", "356683", "356695", "356626", "356638", "356705", "356569", "356653", "356583", "356665", "356593", "356676", "356605", "356691", "356618", "356631", "356646", "356659", "356702", "356672", "356684", "356566", "356580", "356590", "356697", "356601", "356615"], "data": {"356659": {"propaddres": 5020, "proaddress": "5020 LAFONTAINE", "parcelnumb": "21078584.", "fid": 356659, "ownername1": "JANKOWSKI, TED"}, "356586": {"propaddres": 5075, "proaddress": "5075 ASHLEY", "parcelnumb": "21078684.", "fid": 356586, "ownername1": "KOIKAS, ATHANASIOS"}, "356580": {"propaddres": 5057, "proaddress": "5057 LAFONTAINE", "parcelnumb": "21078615.", "fid": 356580, "ownername1": "JOSEPH, THOMAS A"}, "356583": {"propaddres": 5070, "proaddress": "5070 LAFONTAINE", "parcelnumb": "21078590.", "fid": 356583, "ownername1": "LAWLER, BERNADETTE"}, "356601": {"propaddres": 5039, "proaddress": "5039 LAFONTAINE", "parcelnumb": "21078617.", "fid": 356601, "ownername1": "VERBEJE, JAMES R"}, "356705": {"propaddres": 5008, "proaddress": "5008 ASHLEY", "parcelnumb": "21078640.", "fid": 356705, "ownername1": "SMART DEALS INVESTMENTS LLC"}, "356646": {"propaddres": 5028, "proaddress": "5028 LAFONTAINE", "parcelnumb": "21078585.", "fid": 356646, "ownername1": "ZILINSKI, OLGA"}, "356702": {"propaddres": 4995, "proaddress": "4995 ASHLEY", "parcelnumb": "21078693.", "fid": 356702, "ownername1": "WITHERS, THOMAS F"}, "356605": {"propaddres": 5056, "proaddress": "5056 LAFONTAINE", "parcelnumb": "21078588.", "fid": 356605, "ownername1": "BLACK, HELEN K"}, "356626": {"propaddres": 5047, "proaddress": "5047 ASHLEY", "parcelnumb": "21078687.", "fid": 356626, "ownername1": "BANK OF NEW YORK MELLON"}, "356574": {"propaddres": 5085, "proaddress": "5085 ASHLEY", "parcelnumb": "21078683.", "fid": 356574, "ownername1": "COLEMAN, LATRICIA"}, "356638": {"propaddres": 5041, "proaddress": "5041 ASHLEY", "parcelnumb": "21078688.", "fid": 356638, "ownername1": "GREENE, DAN J"}, "356672": {"propaddres": 5010, "proaddress": "5010 LAFONTAINE", "parcelnumb": "21078583.", "fid": 356672, "ownername1": "KOTULA, MARK E"}, "356671": {"propaddres": 5038, "proaddress": "5038 ASHLEY", "parcelnumb": "21078643.", "fid": 356671, "ownername1": "ROKANSAS, THOMAS L"}, "356676": {"propaddres": 5007, "proaddress": "5007 ASHLEY", "parcelnumb": "21078691.", "fid": 356676, "ownername1": "ALLIED REALTY & INVESTMENT CORP"}, "356695": {"propaddres": 5018, "proaddress": "5018 ASHLEY", "parcelnumb": "21078641.", "fid": 356695, "ownername1": "WALKER, HOWARD"}, "356697": {"propaddres": 4992, "proaddress": "4992 LAFONTAINE", "parcelnumb": "21078581.", "fid": 356697, "ownername1": "JANKOWSKI, ADAM"}, "356691": {"propaddres": 5003, "proaddress": "5003 ASHLEY", "parcelnumb": "21078692.", "fid": 356691, "ownername1": "SNEED, LATOYA"}, "356615": {"propaddres": 5031, "proaddress": "5031 LAFONTAINE", "parcelnumb": "21078618.", "fid": 356615, "ownername1": "LOOMIS, ROBERT & WELLS, PEARSON"}, "356593": {"propaddres": 5062, "proaddress": "5062 LAFONTAINE", "parcelnumb": "21078589.", "fid": 356593, "ownername1": "GOOLSBY, DENISE"}, "356590": {"propaddres": 5049, "proaddress": "5049 LAFONTAINE", "parcelnumb": "21078616.", "fid": 356590, "ownername1": "JIMCO PROPERTIES"}, "356612": {"propaddres": 5057, "proaddress": "5057 ASHLEY", "parcelnumb": "21078686.", "fid": 356612, "ownername1": "MOORE, CLARA M"}, "356653": {"propaddres": 5031, "proaddress": "5031 ASHLEY", "parcelnumb": "21078689.", "fid": 356653, "ownername1": "HAWK, PAUL"}, "356618": {"propaddres": 5046, "proaddress": "5046 LAFONTAINE", "parcelnumb": "21078587.", "fid": 356618, "ownername1": "FEDERAL NATIONAL MORTGAGE ASSOC"}, "356631": {"propaddres": 5036, "proaddress": "5036 LAFONTAINE", "parcelnumb": "21078586.", "fid": 356631, "ownername1": "HOME VANTAGE, LLC"}, "356599": {"propaddres": 5065, "proaddress": "5065 ASHLEY", "parcelnumb": "21078685.", "fid": 356599, "ownername1": "ADAMS, DON D SR"}, "356569": {"propaddres": 5084, "proaddress": "5084 LAFONTAINE", "parcelnumb": "21078591.", "fid": 356569, "ownername1": "YOUNG, DEONTE"}, "356566": {"propaddres": 5065, "proaddress": "5065 LAFONTAINE", "parcelnumb": "21078614.", "fid": 356566, "ownername1": "MITCHELL, FRANK R"}, "356665": {"propaddres": 5021, "proaddress": "5021 ASHLEY", "parcelnumb": "21078690.", "fid": 356665, "ownername1": "DONALDSON, CHARLES & SPALDING, THER"}, "356684": {"propaddres": 5000, "proaddress": "5000 LAFONTAINE", "parcelnumb": "21078582.", "fid": 356684, "ownername1": "BRAVO LLC"}, "356683": {"propaddres": 5028, "proaddress": "5028 ASHLEY", "parcelnumb": "21078642.", "fid": 356683, "ownername1": "JUNIOUS, LEONARD"}}, "grid": ["    !!!!!!!!!#########$$$%%%%%%%%%%%%%%%%%%%%%%%&'''''''''((((((", "    !!!!!!!!!########$$$$$$%%%%%%%%%%%%%%%%%%%%%%%''''''''((((((", "   !!!!!!!!!#########$$$$$$$$%%%%%%%%%%%%%%%%%%%%%%%'''''(((((((", "   !!!!!!!!#########$$$$$$$$$))%%%%%%%%%%%%%%%%%%%%%%''''(((((((", "  !!!!!!!!!#########$$$$$$$$$)))%%%%%%%%%%%%%%%%%%%%%%%'((((((((", "  !!!!!!!!#########$$$$$$$$$))))))%%%%%%%%%%%%%%%%%%%%%%%(((((((", " !!!!!!!!!#########$$$$$$$$$))))))))%%%%%%%%%%%%%%%%%%%%%%%(((((", "!!!!!!!!!#########$$$$$$$$$)))))))))**%%%%%%%%%%%%%%%%%%%%%%%((+", "!!!!!!!!!#########$$$$$$$$)))))))))*****%%%%%%%%%%%%%%%%%%%%%%%+", "!!!!!!!!#########$$$$$$$$$)))))))))******%%%%%%%%%%%%%%%%%%%%%%%", "!!!!!!!!########$$$$$$$$$)))))))))*********%%%%%%%%%%%%%%%%%%%%%", ",!!!!!!#########$$$$$$$$$)))))))))*********--%%%%%%%%%%%%%%%%%%%", ",,,!!!!########$$$$$$$$$)))))))))*********-----%%%%%%%%%%%%%%%%%", ",,,,!!#########$$$$$$$$$)))))))))********--------%%%%%%%%%%%%%%%", ",,,,,.########$$$$$$$$$)))))))))*********---------/%%%%%%%%%%%%%", ",,,,,...######$$$$$$$$$))))))))*********---------///%%%%%%%%%%%%", ",,,,......###$$$$$$$$$)))))))))*********---------/////%%%%%%%%%%", ",,,,........#$$$$$$$$)))))))))*********---------////////%%%%%%%%", ",,,.........00$$$$$$$)))))))))*********---------///////111%%%%%%", ",,,.........000$$$$$)))))))))*********---------////////11111%%%%", ",,.........000000$$$)))))))))*********--------////////1111111%%%", ",,........000000000)))))))))*********---------////////111111111%", ",.........00000000022)))))))*********--------////////11111111113", ".........00000000022222))))*********---------////////11111111113", ".........000000000222222))*********---------////////111111111133", "........000000000222222222*********---------////////111111111333", "........00000000022222222444******---------////////1111111111333", ".......00000000022222222244444****---------////////1111111113333", ".......0000000022222222244444444*---------////////11111111113333", "......000000000222222222444444444---------///////111111111133333", ".....000000000222222222444444444555------////////111111111133333", ".....00000000022222222244444444455555---////////1111111111333333", "....00000000022222222244444444455555555-////////1111111111333333", "....0000000002222222224444444455555555566//////11111111113333333", "...0000000002222222224444444445555555556666////11111111113333333", "%..00000000022222222444444444555555555666666//111111111133333333", "%%%0000000022222222244444444455555555566666666111111111333333333", "%%%%%00000222222222444444444555555555666666666771111111333333333", "%%%%%%%000222222222444444444555555555666666667777711113333333338", "%%%%%%%%%2222222224444444445555555556666666667777777113333333338", "%%%%%%%%%%222222224444444445555555566666666677777777733333333388", "%%%%%%%%%%%%2222244444444455555555566666666677777777799333333388", "%%%%%%%%%%%%%%22244444444555555555666666666777777777999993333888", "%%%%%%%%%%%%%%%%444444444555555555666666666777777777999999938888", "%%%%%%%%%%%%%%%%%%444444555555555666666666777777777999999999:888", "%%%%%%%%%%%%%%%%%%%4444455555555566666666677777777999999999::::8", ";%%%%%%%%%%%%%%%%%%%%44555555555666666666777777777999999999:::::", ";;;%%%%%%%%%%%%%%%%%%%%55555555566666666777777777999999999::::::", ";;;;<%%%%%%%%%%%%%%%%%%%%555555666666666777777777999999999::::::", ";;;;<<<%%%%%%%%%%%%%%%%%%%%555666666666777777777999999999:::::::", ";;;<<<<<%%%%%%%%%%%%%%%%%%%%%5666666666777777777999999999:::::::", ";;;<<<<<<<%%%%%%%%%%%%%%%%%%%%66666666777777777999999999::::::::", ";;<<<<<<<<<=%%%%%%%%%%%%%%%%%%%%66666677777777799999999:::::::::", ";<<<<<<<<<====%%%%%%%%%%%%%%%%%%%%666777777777999999999:::::::::", ";<<<<<<<<<======%%%%%%%%%%%%%%%%%%%%677777777999999999:::::::::>", "<<<<<<<<<========%%%%%%%%%%%%%%%%%%%%%7777777999999999:::::::::>", "<<<<<<<<<=========?%%%%%%%%%%%%%%%%%%%%77777999999999:::::::::>>", "<<<<<<<<=========????%%%%%%%%%%%%%%%%%%%%777999999999:::::::::>>", "<<<<<<<<========???????%%%%%%%%%%%%%%%%%%%%999999999:::::::::>>>", "<<<<<<<=========?????????%%%%%%%%%%%%%%%%%%%%9999999::::::::>>>>", "<<<<<<=========?????????@@%%%%%%%%%%%%%%%%%%%%%9999:::::::::>>>>", "<<<<<<=========?????????@@@@%%%%%%%%%%%%%%%%%%%%%9:::::::::>>>>>", "<<<<<=========?????????@@@@@@@%%%%%%%%%%%%%%%%%%%%:::::::::>>>>>", "<<<<<=========?????????@@@@@@@@@%%%%%%%%%%%%%%%%%%%%::::::>>>>>>"]}