{"keys": ["9988", "", "10056", "9999"], "data": {"9999": {"propaddres": 7201, "proaddress": "7201 CLAYTON", "parcelnumb": "18001684.003L", "fid": 9999, "ownername1": "CONSLOIDATED RAIL CORP"}, "10056": {"propaddres": 3401, "proaddress": "3401 MARTIN", "parcelnumb": "18001561-4", "fid": 10056, "ownername1": "MNP CORP"}, "9988": {"propaddres": 3601, "proaddress": "3601 PARKINSON", "parcelnumb": "18001684.002", "fid": 9988, "ownername1": "GAL-CRO STEEL"}}, "grid": ["                !!!!!!!!!!!!!!!!!###############################", "                !!!!!!!!!!!!!!!!################################", "                 !!!!!!!!!!!!!##################################", "                 !!!!!!!!!!!####################################", "                  !!!!!!!!!#####################################", "                  !!!!!!!#######################################", "                   !!!!#########################################", "                   !!   ########################################", "                        ########################################", "                         #######################################", "                         #######################################", "                          ######################################", "                          ######################################", "                           #####################################", "                           #####################################", "                            ####################################", "                            ####################################", "                             ###################################", "                             ###################################", "                              ##################################", "                               #################################", "                               #################################", "                                ################################", "                                ################################", "                                 ###############################", "                                 ###############################", "                                  ##############################", "                                  ##############################", "                                   #############################", "                                   #############################", "                                    ############################", "                                    ############################", "                                    $###########################", "                              $$$$$$$###########################", "                         $$$$$$$$$$$$###########################", "                    $$$$$$$$$$$$$$$$$###########################", "              $$$$$$$$$$$$$$$$$$$$$$$###########################", "         $$$$$$$$$$$$$$$$$$$$$$$$$$$$###########################", "    $$$$$$$$$$$$$$$$$$$$$$$$$$$$$$$$$$##########################", "$$$$$$$$$$$$$$$$$$$$$$$$$$$$$$$$$$$$$$##########################", "$$$$$$$$$$$$$$$$$$$$$$$$$$$$$$$$$$$$$$##########################", "$$$$$$$$$$$$$$$$$$$$$$$$$$$$$$$$$$$$$$##########################", "$$$$$$$$$$$$$$$$$$$$$$$$$$$$$$$$$$$$$$##########################", "$$$$$$$$$$$$$$$$$$$$$$$$$$$$$$$$$$$$$$##########################", "$$$$$$$$$$$$$$$$$$$$$$$$$$$$$$$$$$$$$$##########################", "$$$$$$$$$$$$$$$$$$$$$$$$$$$$$$$$$$$$$$##########################", "$$$$$$$$$$$$$$$$$$$$$$$$$$$$$$$$$$$$$$##########################", "$$$$$$$$$$$$$$$$$$$$$$$$$$$$$$$$$$$$$$##########################", "$$$$$$$$$$$$$$$$$$$$$$$$$$$$$$$$$$$$$$##########################", "$$$$$$$$$$$$$$$$$$$$$$$$$$$$$$$$$$$$$$##########################", "$$$$$$$$$$$$$$$$$$$$$$$$$$$$$$$$$$$$$$$##############!!!!!!!!!!!", "$$$$$$$$$$$$$$$$$$$$$$$$$$$$$$$$$$$!!!!!!!!!!!!!!!!!!!!!!!!!!!!!", "$$$$$$$$$$$$$$$$$!!!!!!!!!!!!!!!!!!!!!!!!!!!!!!!!!!!!!!!!!!!!!!!", "!!!!!!!!!!!!!!!!!!!!!!!!!!!!!!!!!!!!!!!!!!!!!!!!!!!!!!!!!!!!!!!!", "!!!!!!!!!!!!!!!!!!!!!!!!!!!!!!!!!!!!!!!!!!!!!!!!!!!!!!!!!!!!!!!!", "!!!!!!!!!!!!!!!!!!!!!!!!!!!!!!!!!!!!!!!!!!!!!!!!!!!!!!!!!!!!!!!!", "!!!!!!!!!!!!!!!!!!!!!!!!!!!!!!!!!!!!!!!!!!!!!!!!!!!!!!!!!!!!!!!!", "!!!!!!!!!!!!!!!!!!!!!!!!!!!!!!!!!!!!!!!!!!!!!!!!!!!!!!!!!!!!!!!!", "!!!!!!!!!!!!!!!!!!!!!!!!!!!!!!!!!!!!!!!!!!!!!!!!!!!!!!!!!!!!!!!!", "!!!!!!!!!!!!!!!!!!!!!!!!!!!!!!!!!!!!!!!!!!!!!!!!!!!!!!!!!!!!!!!!", "!!!!!!!!!!!!!!!!!!!!!!!!!!!!!!!!!!!!!!!!!!!!!!!!!!!!!!!!!!!!!!!!", "!!!!!!!!!!!!!!!!!!!!!!!!!!!!!!!!!!!!!!!!!!!!!!!!!!!!!!!!!!!!!!!!", "!!!!!!!!!!!!!!!!!!!!!!!!!!!!!!!!!!!!!!!!!!!!!!!!!!!!!!!!!!!!!!!!", "!!!!!!!!!!!!!!!!!!!!!!!!!!!!!!!!!!!!!!!!!!!!!!!!!!!!!!!!!!!!!!!!"]}