{"keys": ["361176", "361184", "361188", "", "225142", "225147", "225153", "225160", "225166", "225136", "361164", "361209", "361217", "361195", "361220", "361185", "225165", "225157", "361226", "361178", "361230", "361211", "361203", "361193", "225169"], "data": {"361220": {"propaddres": 7719, "proaddress": "7719 LINWOOD", "parcelnumb": "10007715.", "fid": 361220, "ownername1": "PAN-AFRICAN ORTH CHRIST CH"}, "361230": {"propaddres": 7701, "proaddress": "7701 LINWOOD", "parcelnumb": "10007717.", "fid": 361230, "ownername1": "PAN-AFRICAN ORTH CHRIST CH"}, "361185": {"propaddres": 2637, "proaddress": "2637 COLUMBUS", "parcelnumb": "10001439.", "fid": 361185, "ownername1": "DAVIS, JANICE"}, "361184": {"propaddres": 8023, "proaddress": "8023 LINWOOD", "parcelnumb": "10007711.", "fid": 361184, "ownername1": "NEW BIRTH CHURCH OF CHRIST"}, "361217": {"propaddres": 7735, "proaddress": "7735 LINWOOD", "parcelnumb": "10007714.", "fid": 361217, "ownername1": "CITY OF DETROIT-P&DD"}, "361164": {"propaddres": 2638, "proaddress": "2638 COLUMBUS", "parcelnumb": "10001472-3", "fid": 361164, "ownername1": "ADAMS, BERNICE"}, "361188": {"propaddres": 8017, "proaddress": "8017 LINWOOD", "parcelnumb": "10007712.", "fid": 361188, "ownername1": "NEW BIRTH CHURCH OF CHRIST"}, "361211": {"propaddres": 2632, "proaddress": "2632 WHITNEY", "parcelnumb": "10001437.", "fid": 361211, "ownername1": "HUGHES, MARK WUENTIN"}, "225169": {"propaddres": 7650, "proaddress": "7650 LINWOOD", "parcelnumb": "10007428.004", "fid": 225169, "ownername1": "MCCOY-SMITH, RENITA"}, "225166": {"propaddres": 2516, "proaddress": "2516 S LA SALLE GARDENS", "parcelnumb": "10001276.", "fid": 225166, "ownername1": "STEPHENS, MARIAN C"}, "225142": {"propaddres": 2550, "proaddress": "2550 S LA SALLE GARDENS", "parcelnumb": "10001272.", "fid": 225142, "ownername1": "STEPHENS, RUTH R"}, "225165": {"propaddres": 2545, "proaddress": "2545 S LA SALLE GARDENS", "parcelnumb": "10001269.", "fid": 225165, "ownername1": "SIOFI, LLC"}, "225160": {"propaddres": 2530, "proaddress": "2530 S LA SALLE GARDENS", "parcelnumb": "10001275.", "fid": 225160, "ownername1": "CITY OF DETROIT-TAXABLE"}, "225147": {"propaddres": 2540, "proaddress": "2540 S LA SALLE GARDENS", "parcelnumb": "10001273.", "fid": 225147, "ownername1": "DORIS WEEMS LIVING TRUST"}, "361226": {"propaddres": 7715, "proaddress": "7715 LINWOOD", "parcelnumb": "10007716.", "fid": 361226, "ownername1": "PAN-AFRICAN ORTH CHRIST CH"}, "361195": {"propaddres": 2631, "proaddress": "2631 COLUMBUS", "parcelnumb": "10001438.", "fid": 361195, "ownername1": "DAVIS, JANICE"}, "361203": {"propaddres": 2638, "proaddress": "2638 WHITNEY", "parcelnumb": "10001436.", "fid": 361203, "ownername1": "HUGHES, MARK Q SR"}, "361178": {"propaddres": 2645, "proaddress": "2645 COLUMBUS", "parcelnumb": "10001440.", "fid": 361178, "ownername1": "DAVIS, JANICE"}, "361193": {"propaddres": 2646, "proaddress": "2646 WHITNEY", "parcelnumb": "10001435.", "fid": 361193, "ownername1": "HUGHES, M M"}, "361176": {"propaddres": 8045, "proaddress": "8045 LINWOOD", "parcelnumb": "10007710.001", "fid": 361176, "ownername1": "ATTY, JIM & KHALIDA"}, "361209": {"propaddres": 7731, "proaddress": "7731 LINWOOD", "parcelnumb": "10007713.", "fid": 361209, "ownername1": "CITY OF DETROIT-P&DD"}, "225157": {"propaddres": 2553, "proaddress": "2553 S LA SALLE GARDENS", "parcelnumb": "10001270.", "fid": 225157, "ownername1": "FUNDERBURK, GRADY G"}, "225153": {"propaddres": 2534, "proaddress": "2534 S LA SALLE GARDENS", "parcelnumb": "10001274.", "fid": 225153, "ownername1": "COLLIER, N"}, "225136": {"propaddres": 2554, "proaddress": "2554 S LA SALLE GARDENS", "parcelnumb": "10001271.", "fid": 225136, "ownername1": "WHITE, BENNIE JR"}}, "grid": ["   !!!!!!!!!!!####$$$$$$$$$$$$$$$$$$%%%%%%%&&&&&&'''''''((((((()", " !!!!!!!!!!!!######$$$$$$$$$$$$$$$**%%%%%%%&&&&&&&'''''''(((((()", "!!!!!!!!!!!########$$$$$$$$$$$$$*****%%%%%%%&&&&&&'''''''(((((((", "!!!!!!!!!###########$$$$$$$$$$*******%%%%%%%&&&&&&&'''''''((((((", "!!!!!!!#############$$$$$$$$$$$*******%%%%%%%&&&&&&'''''''((((((", "!!!!!################$$$$$$$$$$*******%%%%%%%&&&&&&&'''''''(((((", "!!!##################$$$$$$$$$$$*******%%%%%%%&&&&&&'''''''(((((", "!#####################$$$$$$$$$$*******%%%%%%%&&&&&&&'''''''((((", "######################$$$$$$$$$$$*******%%%%%%%&&&&&&'''''''((((", "#######################$$$$$$$$$$*******%%%%%%%&&&&&&&'''''''(((", "#######################$$$$$$$$$$$*******%%%%%%%&&&&&&'''''''(((", "########################$$$$$$$$$$*******%%%%%%%&&&&&&&'''''''((", "$#######################$$$$$$$$$$$*******%%%%%%%&&&&&&'''''''((", "$########################$$$$$$$$$$*******%%%%%%%&&&&&&&'''''''(", "$$#######################$$$$$$$$$$$*******%%%%%%%&&&&&&'''''''(", "$$#######################$$$$$$$$$$$*******%%%%%%%&&&&&&&'''''''", "$$#####################$$$$$$$$$$$$$$*******%%%%%%%&&&&&&'''''''", "$$$##################$$$$$$$$$$$$$$$$*******%%%%%%%&&&&&&&''''''", "+$$################$$$$$$$$$$$$$$$$$$$*******%%%%%%%&&&&&&''''''", "+$$$#############$$$$$$$$$$$$$$$$$$$$$*******%%%%%%%&&&&&&&'''''", "+$$$###########$$$$$$$$$$$$$$$$$$$$$$$$*******%%%%%%%&&&&&&'''''", "++$$$########$$$$$$$$$$$$$$$$$$$$$$$$$$*******%%%%%%%&&&&&&&''''", "++$$$######$$$$$$$$$$$$$$$$$$$$$$$$$$$$$*******%%%%%%%&&&&&&''''", "+++$$$###$$$$$$$$$$$$$$$$$$$$$$$$$$$$$$$*******%%%%%%%&&&&&&&'''", "+++$$$#$$$$$$$$$$$$$$$$$$$$$,,$$$$$$$$$$$*******%%%%%%%&&&&&&'''", "++++$$$$$$$$$$$$$$$$$$$$$$,,,,$$$$$$$$$$$*******%%%%%%%&&&&&&&''", "+++$$$$$$$$$$$$$$$$$$$$$$,,,,,,$$$$$$$$$$$*******%%%%%%%&&&&&&''", "+$$$$$$$$$$$$$$$$$$$$$$,,,,,,,,$$$$$$$$$$$*******%%%%%%%&&&&&&&'", "$$$$$$$$$$$$$$$$$$$$$,,,,,,,,,,,$$$$$$$$$$$*******%%%%%%&&&&&&$$", "$$$$$$$$$$$$$$$$$$$,,,,,,,,,,,,,$$$$$$$$$$$*******%%%%%%%&&&$$$$", "$$$$$$$$$$$$$$$$$,,,,,,,,,,,,,,,-$$$$$$$$$$$*******%%%%%%&$$$$$$", "$$$$$$$$$$$$$$$,,,,,,,,,,,,,,,---$$$$$$$$$$$*******%%%%%$$$$$$$$", "$$$$$$$$$$$$$,,,,,,,,,,,,,,,------$$$$$$$$$$$*******%%$$$$$$$$$$", "$$$$$$$$$$$,,,,,,,,,,,,,,,--------$$$$$$$$$$$*******$$$$$$$$$$$$", "$$$$$$$$$$$,,,,,,,,,,,,,-----------$$$$$$$$$$$****$$$$$$$$$$$$$$", "$$$$$$$...$$,,,,,,,,,,------------/$$$$$$$$$$$**$$$$$$$$$$$$$$$$", "$$$$$.....$$,,,,,,,,------------////$$$$$$$$$$$$$$$$$$$$$$$$$$$$", "$$$........$$,,,,,------------//////$$$$$$$$$$$$$$$$$$$$$$$$$$$$", "$00........$$,,,,-----------/////////$$$$$$$$$$$$$$$$$$$$$$$$$$$", "000.........$$,-----------///////////$$$$$$$$$$$$$$$$$$$$$$$$$$1", "0000........$$----------//////////////$$$$$$$$$$$$$$$$$$$$$$$111", "0000.........$$-------////////////////$$$$$$$$$$$$$$$$$$$$$11111", "00000........$$-----///////////////////$$$$$$$$$$$$$$$$$$1111111", "00000.........$$--/////////////////////$$$$$$$$$$$$$$$$222111111", "000000........$$///////////////////////3$$$$$$$$$$$$$22222111111", "000000.........$$////////////////////333$$$$$$$$$$$2222222211111", "0000000........$$//////////////////333333$$$$$$$$$$2222222211111", "0000000.........$$///////////////33333333$$$$$$$$$$$222222221111", "40000000........$$/////////////33333333333$$$$$$$$$$222222221111", "40000000.........$$//////////3333333333335$$$$$$$$$$$22222222111", "440000000........$$////////3333333333335555$$$$$$$$$$22222222111", "440000000.........$$/////333333333333555555$$$$$$$$$$$2222222211", "4440000000......$$$$///333333333333555555555$$$$$$$$$$2222222211", "4440000000....$$$$$$$33333333333355555555555$$$$$$$$$$$222222221", "44440000000.$$$$$6$$$333333333355555555555555$$$$$$$$$$222222221", "4444000000$$$$$6666$$$33333335555555555555555$$$$$$$$$$$22222222", "44444000$$$$$666666$$$333335555555555555555555$$$$$$$$$$22222222", "444440$$$$$666666666$$$33555555555555555555555$$$$$$$$$$$2222222", "4444$$$$$77766666666$$$555555555555555555555555$$$$$$$$$$2222222", "44$$$$$77777666666666$$$55555555555555555555555$$$$$$$$$$$222222", "$$$$$8777777766666666$$$55555555555555555555555$$$$$$$$$$$222299", "$$$8887777777666666666$$555555555555555555555$$$$$$$$$$$$$$29999", "$888888777777666666666$$$555555555555555555$$$$$$$$$$$$$$$$99999", "8888888777777766666666$$$5555555555555555$$$$$$$$$$$$$$$$$$$9999"]}